[{"tag":{"title":"Kiểm tra môn Luyện thi 5+ môn Toán - HOCMAI"},"title":"Bài tập tự luyện","subtitle":"ĐỀ KIỂM TRA ĐẦU VÀO","questions":[{"content":"\n    Đạo hàm của hàm số \\[y=\\log ({{x}^{2}}+x+1)\\] là","info":"\n\t1.\n      ","answers":[{"content":"\n                <label for=\"resp791802_2371494\">\n                    <span class=\"under_an\">A</span>. \\[y'=\\frac{1}{{{x}^{2}}+x+1}\\].                </label>\n            ","id":"resp791802_2371494","value":"2371494"},{"content":"\n                <label for=\"resp791802_2371496\">\n                    <span class=\"under_an\">B</span>. \\[y'=\\frac{(2x+1)\\ln 10}{{{x}^{2}}+x+1}\\].                </label>\n            ","id":"resp791802_2371496","value":"2371496"},{"content":"\n                <label for=\"resp791802_2371498\">\n                    <span class=\"under_an\">C</span>. \\[y'=\\frac{2x+1}{{{x}^{2}}+x+1}\\].                </label>\n            ","id":"resp791802_2371498","value":"2371498"},{"content":"\n                <label for=\"resp791802_2371500\">\n                    <span class=\"under_an\">D</span>. \\[y'=\\frac{2x+1}{({{x}^{2}}+x+1)\\ln 10}\\].                </label>\n            ","id":"resp791802_2371500","value":"2371500"}]},{"content":"\n    Trong không gian với hệ tọa độ \\[Oxyz\\], cho điểm \\[A(-1;2;4)\\]. Điểm nào sau đây là hình chiếu vuông góc của điểm \\[A\\] trên mặt phẳng \\[(Oyz)\\]?","info":"\n\t2.\n      ","answers":[{"content":"\n                <label for=\"resp791804_2371486\">\n                    <span class=\"under_an\">A</span>. \\[M(-1;0;0)\\].                </label>\n            ","id":"resp791804_2371486","value":"2371486"},{"content":"\n                <label for=\"resp791804_2371488\">\n                    <span class=\"under_an\">B</span>. \\[N(0;2;4)\\].                </label>\n            ","id":"resp791804_2371488","value":"2371488"},{"content":"\n                <label for=\"resp791804_2371490\">\n                    <span class=\"under_an\">C</span>. \\[P(-1;0;4)\\].                </label>\n            ","id":"resp791804_2371490","value":"2371490"},{"content":"\n                <label for=\"resp791804_2371492\">\n                    <span class=\"under_an\">D</span>. \\[Q(-1;2;0)\\].                </label>\n            ","id":"resp791804_2371492","value":"2371492"}]},{"content":"\n    Cho số phức \\[z\\] thỏa mãn \\[{{(1+z)}^{2}}\\] là số thực. Tập hợp diểm \\[M\\] biểu diễn số phức \\[z\\] là","info":"\n\t3.\n      ","answers":[{"content":"\n                <label for=\"resp791806_2371550\">\n                    <span class=\"under_an\">A</span>. Đường tròn.                </label>\n            ","id":"resp791806_2371550","value":"2371550"},{"content":"\n                <label for=\"resp791806_2371552\">\n                    <span class=\"under_an\">B</span>. Parabol.                </label>\n            ","id":"resp791806_2371552","value":"2371552"},{"content":"\n                <label for=\"resp791806_2371554\">\n                    <span class=\"under_an\">C</span>. Một đường thẳng.                </label>\n            ","id":"resp791806_2371554","value":"2371554"},{"content":"\n                <label for=\"resp791806_2371556\">\n                    <span class=\"under_an\">D</span>. Hai đường thẳng.                </label>\n            ","id":"resp791806_2371556","value":"2371556"}]},{"content":"\n    Biết \\[\\int\\limits_{3}^{4}{\\frac{dx}{(x+1)(x-2)}}=a\\ln 2+b\\ln 5+c\\], với \\[a,b,c\\] là các số hữu tỉ. Tính \\[S=a-3b+c\\].","info":"\n\t4.\n      ","answers":[{"content":"\n                <label for=\"resp791808_2371566\">\n                    <span class=\"under_an\">A</span>. \\[S=3\\].                </label>\n            ","id":"resp791808_2371566","value":"2371566"},{"content":"\n                <label for=\"resp791808_2371568\">\n                    <span class=\"under_an\">B</span>. \\[S=2\\].                </label>\n            ","id":"resp791808_2371568","value":"2371568"},{"content":"\n                <label for=\"resp791808_2371570\">\n                    <span class=\"under_an\">C</span>. \\[S=-2\\].                </label>\n            ","id":"resp791808_2371570","value":"2371570"},{"content":"\n                <label for=\"resp791808_2371572\">\n                    <span class=\"under_an\">D</span>. \\[S=0\\].                </label>\n            ","id":"resp791808_2371572","value":"2371572"}]},{"content":"\n    Gọi \\[S\\] là diện tích hình phẳng giới hạn bởi đồ thị hàm số \\[y=f(x)\\], trục hoành, đường thẳng \\[x=a\\], \\[x=b\\] (như hình bên). Hỏi cách tính \\[S\\] nào dưới đây đúng?","info":"\n\t5.\n      ","answers":[{"content":"\n                <label for=\"resp791810_2371502\">\n                    <span class=\"under_an\">A</span>. \\[S=\\int\\limits_{a}^{b}{f(x)dx}\\].                </label>\n            ","id":"resp791810_2371502","value":"2371502"},{"content":"\n                <label for=\"resp791810_2371504\">\n                    <span class=\"under_an\">B</span>. \\[S=\\left| \\int\\limits_{a}^{c}{f(x)dx}+\\int\\limits_{c}^{b}{f(x)dx} \\right|\\].                </label>\n            ","id":"resp791810_2371504","value":"2371504"},{"content":"\n                <label for=\"resp791810_2371506\">\n                    <span class=\"under_an\">C</span>. \\[S=-\\int\\limits_{a}^{c}{f(x)dx}+\\int\\limits_{c}^{b}{f(x)dx}\\].                </label>\n            ","id":"resp791810_2371506","value":"2371506"},{"content":"\n                <label for=\"resp791810_2371508\">\n                    <span class=\"under_an\">D</span>. \\[S=\\int\\limits_{a}^{c}{f(x)dx}+\\int\\limits_{c}^{b}{f(x)dx}\\].                </label>\n            ","id":"resp791810_2371508","value":"2371508"}]},{"content":"\n    Cho hình chóp $$ S. ABCD $$ có đáy $$ ABCD $$ là hình vuông cạnh $$ a $$ , cạnh bên $$ SA=x $$ và vuông góc với đáy $$ \\left( ABCD \\right). $$ Xác định $$ x $$ để hai mặt phẳng $$ \\left( SBC \\right) $$ và \\[\\left( SCD \\right)\\] hợp với nhau góc $$ 60{}^\\circ . $$","info":"\n\t6.\n      ","answers":[{"content":"\n                <label for=\"resp791812_2371614\">\n                    <span class=\"under_an\">A</span>. $$ x=\\frac{a}{2}. $$                </label>\n            ","id":"resp791812_2371614","value":"2371614"},{"content":"\n                <label for=\"resp791812_2371616\">\n                    <span class=\"under_an\">B</span>. $$ x=a. $$                </label>\n            ","id":"resp791812_2371616","value":"2371616"},{"content":"\n                <label for=\"resp791812_2371618\">\n                    <span class=\"under_an\">C</span>. $$ x=\\frac{3a}{2}. $$                </label>\n            ","id":"resp791812_2371618","value":"2371618"},{"content":"\n                <label for=\"resp791812_2371620\">\n                    <span class=\"under_an\">D</span>. $$ x=2a. $$                </label>\n            ","id":"resp791812_2371620","value":"2371620"}]},{"content":"\n    Cho khối chóp \\[S. ABC\\] có \\[SA,SB,SC\\] đôi một vuông góc và \\[SA=a,SB=b,SC=c\\]. Tính thể tích \\[V\\] của khối chóp \\[S. ABC\\] theo \\[a,b,c\\].","info":"\n\t7.\n      ","answers":[{"content":"\n                <label for=\"resp791814_2371558\">\n                    <span class=\"under_an\">A</span>. \\[V=\\frac{abc}{3}\\].                </label>\n            ","id":"resp791814_2371558","value":"2371558"},{"content":"\n                <label for=\"resp791814_2371560\">\n                    <span class=\"under_an\">B</span>. \\[V=\\frac{abc}{6}\\].                </label>\n            ","id":"resp791814_2371560","value":"2371560"},{"content":"\n                <label for=\"resp791814_2371562\">\n                    <span class=\"under_an\">C</span>. \\[V=\\frac{abc}{2}\\].                </label>\n            ","id":"resp791814_2371562","value":"2371562"},{"content":"\n                <label for=\"resp791814_2371564\">\n                    <span class=\"under_an\">D</span>. \\[V=abc\\].                </label>\n            ","id":"resp791814_2371564","value":"2371564"}]},{"content":"\n    Cho hàm số  $$ y=-{{x}^{3}}+3{{x}^{2}}-5 $$ . Các mệnh để sau mệnh đề nào sai.","info":"\n\t8.\n      ","answers":[{"content":"\n                <label for=\"resp791816_2371478\">\n                    <span class=\"under_an\">A</span>. Hàm số đồng biến  $$ \\left( 0;2 \\right) $$                </label>\n            ","id":"resp791816_2371478","value":"2371478"},{"content":"\n                <label for=\"resp791816_2371480\">\n                    <span class=\"under_an\">B</span>. Hàm số nghịch biến trên  $$ \\left( 3;+\\infty<br>  \\right) $$                </label>\n            ","id":"resp791816_2371480","value":"2371480"},{"content":"\n                <label for=\"resp791816_2371482\">\n                    <span class=\"under_an\">C</span>. Hàm số nghịch biến trên khoảng  $$ \\left( -\\infty ;0 \\right) $$                </label>\n            ","id":"resp791816_2371482","value":"2371482"},{"content":"\n                <label for=\"resp791816_2371484\">\n                    <span class=\"under_an\">D</span>. Hàm đạt cực đại tại  $$ x=0,y=-5 $$                </label>\n            ","id":"resp791816_2371484","value":"2371484"}]},{"content":"\n    Cho  $$ n,k $$  là các số nguyên dương tùy ý thỏa mãn  $$ 0\\le k\\le n $$ . Mệnh đề nào sau đây là đúng?","info":"\n\t9.\n      ","answers":[{"content":"\n                <label for=\"resp791818_2371518\">\n                    <span class=\"under_an\">A</span>. $$ A_{n}^{k}=C_{n}^{n-k} $$                </label>\n            ","id":"resp791818_2371518","value":"2371518"},{"content":"\n                <label for=\"resp791818_2371520\">\n                    <span class=\"under_an\">B</span>. $$ C_{n}^{k}=A_{n}^{n-k} $$                </label>\n            ","id":"resp791818_2371520","value":"2371520"},{"content":"\n                <label for=\"resp791818_2371522\">\n                    <span class=\"under_an\">C</span>. $$ C_{n}^{k}=C_{n}^{n-k} $$                </label>\n            ","id":"resp791818_2371522","value":"2371522"},{"content":"\n                <label for=\"resp791818_2371524\">\n                    <span class=\"under_an\">D</span>. $$ A_{n}^{k}=A_{n}^{n-k} $$                </label>\n            ","id":"resp791818_2371524","value":"2371524"}]},{"content":"\n    Tập nghiệm \\[S\\] của bất phương trình \\[\\log _{2}^{2}x-5{{\\log }_{2}}x-6\\le 0\\] là","info":"\n\t10.\n      ","answers":[{"content":"\n                <label for=\"resp791820_2371574\">\n                    <span class=\"under_an\">A</span>. \\[S=\\left[ \\frac{1}{2};64 \\right]\\].                </label>\n            ","id":"resp791820_2371574","value":"2371574"},{"content":"\n                <label for=\"resp791820_2371576\">\n                    <span class=\"under_an\">B</span>. \\[S=\\left( 0;\\frac{1}{2} \\right]\\].                </label>\n            ","id":"resp791820_2371576","value":"2371576"},{"content":"\n                <label for=\"resp791820_2371578\">\n                    <span class=\"under_an\">C</span>. \\[S=\\left[ 64;+\\infty<br>  \\right)\\].                </label>\n            ","id":"resp791820_2371578","value":"2371578"},{"content":"\n                <label for=\"resp791820_2371580\">\n                    <span class=\"under_an\">D</span>. \\[S=\\left( 0;\\frac{1}{2} \\right]\\cup \\left[ 64;+\\infty<br>  \\right)\\].                </label>\n            ","id":"resp791820_2371580","value":"2371580"}]},{"content":"\n    Nguyên hàm của hàm số  $$ y=\\frac{3x-5}{{{x}^{2}}-3x+2} $$  có dạng  $$ a\\ln \\left| x-1 \\right|+b\\ln \\left| x-2 \\right|+C $$ . Giá trị  $$ a+2b $$  là.","info":"\n\t11.\n      ","answers":[{"content":"\n                <label for=\"resp791822_2371622\">\n                    <span class=\"under_an\">A</span>. $$ \\frac{3}{2} $$                </label>\n            ","id":"resp791822_2371622","value":"2371622"},{"content":"\n                <label for=\"resp791822_2371624\">\n                    <span class=\"under_an\">B</span>. $$ 4 $$                </label>\n            ","id":"resp791822_2371624","value":"2371624"},{"content":"\n                <label for=\"resp791822_2371626\">\n                    <span class=\"under_an\">C</span>. $$ 2 $$                </label>\n            ","id":"resp791822_2371626","value":"2371626"},{"content":"\n                <label for=\"resp791822_2371628\">\n                    <span class=\"under_an\">D</span>. $$ \\frac{4}{3} $$                </label>\n            ","id":"resp791822_2371628","value":"2371628"}]},{"content":"\n    Có hai hộp đựng bi. Hộp thứ nhất đựng 7 bi đỏ và 5 bi xanh. Hộp thứ hai đựng 6 bi đỏ và 4 bi xanh. Từ mỗi hộp lấy ngẫu nhiên một bi, tính xác xuất để 2 bi được lấy ra có cùng màu.","info":"\n\t12.\n      ","answers":[{"content":"\n                <label for=\"resp791824_2371534\">\n                    <span class=\"under_an\">A</span>. \\[\\frac{31}{60}\\].                </label>\n            ","id":"resp791824_2371534","value":"2371534"},{"content":"\n                <label for=\"resp791824_2371536\">\n                    <span class=\"under_an\">B</span>. \\[\\frac{41}{60}\\].                </label>\n            ","id":"resp791824_2371536","value":"2371536"},{"content":"\n                <label for=\"resp791824_2371538\">\n                    <span class=\"under_an\">C</span>. \\[\\frac{51}{60}\\].                </label>\n            ","id":"resp791824_2371538","value":"2371538"},{"content":"\n                <label for=\"resp791824_2371540\">\n                    <span class=\"under_an\">D</span>. \\[\\frac{11}{60}\\].                </label>\n            ","id":"resp791824_2371540","value":"2371540"}]},{"content":"\n    Đồ thị hình bên là của hàm số \\[y=-{{x}^{3}}+3{{x}^{2}}-4\\]. Để phương trình \\[{{x}^{3}}-3{{x}^{2}}+m=0\\] có hai nghiệm phân biệt thì","info":"\n\t13.\n      ","answers":[{"content":"\n                <label for=\"resp791826_2371542\">\n                    <span class=\"under_an\">A</span>. $$ 0&lt;m&lt;4 $$                </label>\n            ","id":"resp791826_2371542","value":"2371542"},{"content":"\n                <label for=\"resp791826_2371544\">\n                    <span class=\"under_an\">B</span>. $$ m=4 $$ .                </label>\n            ","id":"resp791826_2371544","value":"2371544"},{"content":"\n                <label for=\"resp791826_2371546\">\n                    <span class=\"under_an\">C</span>. $$ \\left[ \\begin{array}{l}<br> m=0 \\\\<br> m=4 <br> \\end{array} \\right. $$ .                </label>\n            ","id":"resp791826_2371546","value":"2371546"},{"content":"\n                <label for=\"resp791826_2371548\">\n                    <span class=\"under_an\">D</span>. $$ \\left[ \\begin{array}{l}<br> m=0 \\\\<br> m=-4 <br> \\end{array} \\right. $$ .                </label>\n            ","id":"resp791826_2371548","value":"2371548"}]},{"content":"\n    Cho hình trụ có tổng chu vi hai đáy là \\[12\\pi \\,cm\\] và có chiều cao \\[4cm\\]. Khi đó diện tích toàn phần \\[{{S}_{tp}}\\] của hình trụ là","info":"\n\t14.\n      ","answers":[{"content":"\n                <label for=\"resp791828_2371582\">\n                    <span class=\"under_an\">A</span>. \\[{{S}_{tp}}=18\\pi \\]\\[c{{m}^{2}}\\].                </label>\n            ","id":"resp791828_2371582","value":"2371582"},{"content":"\n                <label for=\"resp791828_2371584\">\n                    <span class=\"under_an\">B</span>. \\[{{S}_{tp}}=24\\pi \\]\\[c{{m}^{2}}\\].                </label>\n            ","id":"resp791828_2371584","value":"2371584"},{"content":"\n                <label for=\"resp791828_2371586\">\n                    <span class=\"under_an\">C</span>. \\[{{S}_{tp}}=33\\pi \\]\\[c{{m}^{2}}\\].                </label>\n            ","id":"resp791828_2371586","value":"2371586"},{"content":"\n                <label for=\"resp791828_2371588\">\n                    <span class=\"under_an\">D</span>. \\[{{S}_{tp}}=42\\pi \\]\\[c{{m}^{2}}\\].                </label>\n            ","id":"resp791828_2371588","value":"2371588"}]},{"content":"\n    Cho hàm số \\[y=f(x)\\] có bảng biến thiên như sau\n Giá trị cực tiểu của hàm số đã cho bằng ","info":"\n\t15.\n      ","answers":[{"content":"\n                <label for=\"resp791830_2371470\">\n                    <span class=\"under_an\">A</span>. \\[-2\\].                </label>\n            ","id":"resp791830_2371470","value":"2371470"},{"content":"\n                <label for=\"resp791830_2371472\">\n                    <span class=\"under_an\">B</span>. \\[0\\].                </label>\n            ","id":"resp791830_2371472","value":"2371472"},{"content":"\n                <label for=\"resp791830_2371474\">\n                    <span class=\"under_an\">C</span>. \\[3\\].                </label>\n            ","id":"resp791830_2371474","value":"2371474"},{"content":"\n                <label for=\"resp791830_2371476\">\n                    <span class=\"under_an\">D</span>. \\[2\\]                </label>\n            ","id":"resp791830_2371476","value":"2371476"}]},{"content":"\n    Một khối tứ diện đều cạnh \\[a\\] có thể tích bằng","info":"\n\t16.\n      ","answers":[{"content":"\n                <label for=\"resp791832_2371510\">\n                    <span class=\"under_an\">A</span>. \\[\\frac{{{a}^{3}}\\sqrt{2}}{6}\\].                </label>\n            ","id":"resp791832_2371510","value":"2371510"},{"content":"\n                <label for=\"resp791832_2371512\">\n                    <span class=\"under_an\">B</span>. \\[\\frac{{{a}^{3}}\\sqrt{3}}{12}\\].                </label>\n            ","id":"resp791832_2371512","value":"2371512"},{"content":"\n                <label for=\"resp791832_2371514\">\n                    <span class=\"under_an\">C</span>. \\[\\frac{{{a}^{3}}\\sqrt{2}}{12}\\].                </label>\n            ","id":"resp791832_2371514","value":"2371514"},{"content":"\n                <label for=\"resp791832_2371516\">\n                    <span class=\"under_an\">D</span>. \\[\\frac{{{a}^{3}}\\sqrt{3}}{6}\\].                </label>\n            ","id":"resp791832_2371516","value":"2371516"}]},{"content":"\n    Trong không gian tọa độ \\[Oxyz\\], cho điểm \\[M(2;-1;0)\\]. Hỏi có bao nhiêu mặt phẳng \\[(P)\\] đi qua \\[M\\] và cắt các trục \\[Ox,Oy,Oz\\] lần lượt tại các điểm \\[A,B,C\\] sao cho \\[OA=2OB=3OC\\ne 0\\]?","info":"\n\t17.\n      ","answers":[{"content":"\n                <label for=\"resp791834_2371606\">\n                    <span class=\"under_an\">A</span>. \\[4\\].                </label>\n            ","id":"resp791834_2371606","value":"2371606"},{"content":"\n                <label for=\"resp791834_2371608\">\n                    <span class=\"under_an\">B</span>. \\[3\\].                </label>\n            ","id":"resp791834_2371608","value":"2371608"},{"content":"\n                <label for=\"resp791834_2371610\">\n                    <span class=\"under_an\">C</span>. \\[2\\].                </label>\n            ","id":"resp791834_2371610","value":"2371610"},{"content":"\n                <label for=\"resp791834_2371612\">\n                    <span class=\"under_an\">D</span>. \\[8\\].                </label>\n            ","id":"resp791834_2371612","value":"2371612"}]},{"content":"\n    Cho hàm số \\[y={{x}^{4}}+{{x}^{2}}-3\\] có đồ thị \\[(C)\\]. Khi đó hệ số góc của tiếp tuyến của đồ thị \\[(C)\\] tại điểm có hoành độ \\[x=1\\] là","info":"\n\t18.\n      ","answers":[{"content":"\n                <label for=\"resp791836_2371590\">\n                    <span class=\"under_an\">A</span>. \\[-1\\].                </label>\n            ","id":"resp791836_2371590","value":"2371590"},{"content":"\n                <label for=\"resp791836_2371592\">\n                    <span class=\"under_an\">B</span>. \\[2\\].                </label>\n            ","id":"resp791836_2371592","value":"2371592"},{"content":"\n                <label for=\"resp791836_2371594\">\n                    <span class=\"under_an\">C</span>. \\[-4\\].                </label>\n            ","id":"resp791836_2371594","value":"2371594"},{"content":"\n                <label for=\"resp791836_2371596\">\n                    <span class=\"under_an\">D</span>. \\[6\\].                </label>\n            ","id":"resp791836_2371596","value":"2371596"}]},{"content":"\n    Trong tất cả các giá trị của \\[m\\] để đồ thị hàm số \\[y=\\frac{x-4}{\\sqrt{m{{x}^{2}}+{{m}^{2}}-17}}\\] có bốn đường tiệm cận, có bao nhiêu giá trị \\[m\\] nguyên?","info":"\n\t19.\n      ","answers":[{"content":"\n                <label for=\"resp791838_2371598\">\n                    <span class=\"under_an\">A</span>. \\[1\\].                </label>\n            ","id":"resp791838_2371598","value":"2371598"},{"content":"\n                <label for=\"resp791838_2371600\">\n                    <span class=\"under_an\">B</span>. \\[2\\].                </label>\n            ","id":"resp791838_2371600","value":"2371600"},{"content":"\n                <label for=\"resp791838_2371602\">\n                    <span class=\"under_an\">C</span>. \\[3\\].                </label>\n            ","id":"resp791838_2371602","value":"2371602"},{"content":"\n                <label for=\"resp791838_2371604\">\n                    <span class=\"under_an\">D</span>. \\[4\\].                </label>\n            ","id":"resp791838_2371604","value":"2371604"}]},{"content":"\n    Cho cấp số nhân có số hạng đầu là  $$ {{u}_{1}}=-2 $$  và số hạng thứ ba là  $$ {{u}_{4}}=-54 $$ . Khi đó, công bội  $$ q $$  bằng","info":"\n\t20.\n      ","answers":[{"content":"\n                <label for=\"resp791840_2371526\">\n                    <span class=\"under_an\">A</span>. $$ \\sqrt[3]{9} $$                </label>\n            ","id":"resp791840_2371526","value":"2371526"},{"content":"\n                <label for=\"resp791840_2371528\">\n                    <span class=\"under_an\">B</span>. $$ -3 $$                </label>\n            ","id":"resp791840_2371528","value":"2371528"},{"content":"\n                <label for=\"resp791840_2371530\">\n                    <span class=\"under_an\">C</span>. $$ 3 $$                </label>\n            ","id":"resp791840_2371530","value":"2371530"},{"content":"\n                <label for=\"resp791840_2371532\">\n                    <span class=\"under_an\">D</span>. $$ -\\sqrt[3]{9} $$                </label>\n            ","id":"resp791840_2371532","value":"2371532"}]}]},{"tag":{"title":"Kiểm tra môn Luyện thi 5+ môn Hóa học - HOCMAI"},"title":"Bài tập tự luyện","subtitle":"ĐỀ KIỂM TRA ĐẦU VÀO","questions":[{"content":"\n    Chất X là một este mạch hở có CTPT là C4H6O2. Số este có CTCT ứng với CTPT đó là","info":"\n\t1.\n      ","answers":[{"content":"\n                <label for=\"resp792666_2374910\">\n                    <span class=\"under_an\">A</span>. 3                </label>\n            ","id":"resp792666_2374910","value":"2374910"},{"content":"\n                <label for=\"resp792666_2374912\">\n                    <span class=\"under_an\">B</span>. 4                </label>\n            ","id":"resp792666_2374912","value":"2374912"},{"content":"\n                <label for=\"resp792666_2374914\">\n                    <span class=\"under_an\">C</span>. 5                </label>\n            ","id":"resp792666_2374914","value":"2374914"},{"content":"\n                <label for=\"resp792666_2374916\">\n                    <span class=\"under_an\">D</span>. 6                </label>\n            ","id":"resp792666_2374916","value":"2374916"}]},{"content":"\n    Hợp chất X có công thức cấu tạo: CH3CH2COOCH3. Tên gọi của X là","info":"\n\t2.\n      ","answers":[{"content":"\n                <label for=\"resp792668_2374918\">\n                    <span class=\"under_an\">A</span>. etyl axetat                </label>\n            ","id":"resp792668_2374918","value":"2374918"},{"content":"\n                <label for=\"resp792668_2374920\">\n                    <span class=\"under_an\">B</span>. metyl propionat                </label>\n            ","id":"resp792668_2374920","value":"2374920"},{"content":"\n                <label for=\"resp792668_2374922\">\n                    <span class=\"under_an\">C</span>. metyl axetat                </label>\n            ","id":"resp792668_2374922","value":"2374922"},{"content":"\n                <label for=\"resp792668_2374924\">\n                    <span class=\"under_an\">D</span>. propyl axetat                </label>\n            ","id":"resp792668_2374924","value":"2374924"}]},{"content":"\n    Este metyl acrylat có công thức là","info":"\n\t3.\n      ","answers":[{"content":"\n                <label for=\"resp792670_2374926\">\n                    <span class=\"under_an\">A</span>. CH3COOCH3.                </label>\n            ","id":"resp792670_2374926","value":"2374926"},{"content":"\n                <label for=\"resp792670_2374928\">\n                    <span class=\"under_an\">B</span>. CH3COOCH=CH2                </label>\n            ","id":"resp792670_2374928","value":"2374928"},{"content":"\n                <label for=\"resp792670_2374930\">\n                    <span class=\"under_an\">C</span>. CH2=CHCOOCH3                </label>\n            ","id":"resp792670_2374930","value":"2374930"},{"content":"\n                <label for=\"resp792670_2374932\">\n                    <span class=\"under_an\">D</span>. HCOOCH3                </label>\n            ","id":"resp792670_2374932","value":"2374932"}]},{"content":"\n    Cho este có công thức cấu tạo : CH2 = C(CH3)COOCH3. Tên gọi của este đó là","info":"\n\t4.\n      ","answers":[{"content":"\n                <label for=\"resp792672_2374934\">\n                    <span class=\"under_an\">A</span>. Metyl acrylat                </label>\n            ","id":"resp792672_2374934","value":"2374934"},{"content":"\n                <label for=\"resp792672_2374936\">\n                    <span class=\"under_an\">B</span>. Metyl metacrylat.                </label>\n            ","id":"resp792672_2374936","value":"2374936"},{"content":"\n                <label for=\"resp792672_2374938\">\n                    <span class=\"under_an\">C</span>. Metyl metacrylic.                </label>\n            ","id":"resp792672_2374938","value":"2374938"},{"content":"\n                <label for=\"resp792672_2374940\">\n                    <span class=\"under_an\">D</span>. Metyl acrylic                </label>\n            ","id":"resp792672_2374940","value":"2374940"}]},{"content":"\n    Thuỷ phân este C2H5COOCH=CH2 trong môi trường axit tạo thành những sản phẩm gì ?","info":"\n\t5.\n      ","answers":[{"content":"\n                <label for=\"resp792674_2374942\">\n                    <span class=\"under_an\">A</span>. C2H5COOH,CH2=CH-OH.                </label>\n            ","id":"resp792674_2374942","value":"2374942"},{"content":"\n                <label for=\"resp792674_2374944\">\n                    <span class=\"under_an\">B</span>. C2H5COOH, HCHO                </label>\n            ","id":"resp792674_2374944","value":"2374944"},{"content":"\n                <label for=\"resp792674_2374946\">\n                    <span class=\"under_an\">C</span>. C2H5COOH, CH3CHO                </label>\n            ","id":"resp792674_2374946","value":"2374946"},{"content":"\n                <label for=\"resp792674_2374948\">\n                    <span class=\"under_an\">D</span>. C2H5COOH, CH3CH2OH                </label>\n            ","id":"resp792674_2374948","value":"2374948"}]},{"content":"\n    Cho các chất: etyl axetat, etanol, axit acrylic, phenol, phenylamoni clorua, phenyl axetat. Số chất tác dụng được với dung dịch NaOH là:","info":"\n\t6.\n      ","answers":[{"content":"\n                <label for=\"resp792676_2374950\">\n                    <span class=\"under_an\">A</span>. 3                </label>\n            ","id":"resp792676_2374950","value":"2374950"},{"content":"\n                <label for=\"resp792676_2374952\">\n                    <span class=\"under_an\">B</span>. 4                </label>\n            ","id":"resp792676_2374952","value":"2374952"},{"content":"\n                <label for=\"resp792676_2374954\">\n                    <span class=\"under_an\">C</span>. 5                </label>\n            ","id":"resp792676_2374954","value":"2374954"},{"content":"\n                <label for=\"resp792676_2374956\">\n                    <span class=\"under_an\">D</span>. 6                </label>\n            ","id":"resp792676_2374956","value":"2374956"}]},{"content":"\n    Cho dãy các chất: phenyl axetat, anlyl axetat, metyl axetat, etyl fomat, tripanmitin. Số chất trong dãy khi thủy phân trong dung dịch NaOH (dư), đun nóng sinh ra ancol là:","info":"\n\t7.\n      ","answers":[{"content":"\n                <label for=\"resp792678_2374958\">\n                    <span class=\"under_an\">A</span>. 4                </label>\n            ","id":"resp792678_2374958","value":"2374958"},{"content":"\n                <label for=\"resp792678_2374960\">\n                    <span class=\"under_an\">B</span>. 2                </label>\n            ","id":"resp792678_2374960","value":"2374960"},{"content":"\n                <label for=\"resp792678_2374962\">\n                    <span class=\"under_an\">C</span>. 5                </label>\n            ","id":"resp792678_2374962","value":"2374962"},{"content":"\n                <label for=\"resp792678_2374964\">\n                    <span class=\"under_an\">D</span>. 3                </label>\n            ","id":"resp792678_2374964","value":"2374964"}]},{"content":"\n    Công thức tổng quát của amin no đơn chức, mạch hở là","info":"\n\t8.\n      ","answers":[{"content":"\n                <label for=\"resp792680_2374966\">\n                    <span class=\"under_an\">A</span>. CnH2n+1N                </label>\n            ","id":"resp792680_2374966","value":"2374966"},{"content":"\n                <label for=\"resp792680_2374968\">\n                    <span class=\"under_an\">B</span>. CnH2n+1NH2.                </label>\n            ","id":"resp792680_2374968","value":"2374968"},{"content":"\n                <label for=\"resp792680_2374970\">\n                    <span class=\"under_an\">C</span>. CnH2n+3N.                </label>\n            ","id":"resp792680_2374970","value":"2374970"},{"content":"\n                <label for=\"resp792680_2374972\">\n                    <span class=\"under_an\">D</span>. CxHyN                </label>\n            ","id":"resp792680_2374972","value":"2374972"}]},{"content":"\n    Trong số các chất : C3H8, C3H7Cl, C3H8O và C3H9N; chất có nhiều đồng phân cấu tạo nhất là","info":"\n\t9.\n      ","answers":[{"content":"\n                <label for=\"resp792682_2374974\">\n                    <span class=\"under_an\">A</span>. C3H7Cl.                </label>\n            ","id":"resp792682_2374974","value":"2374974"},{"content":"\n                <label for=\"resp792682_2374976\">\n                    <span class=\"under_an\">B</span>. C3H8O                </label>\n            ","id":"resp792682_2374976","value":"2374976"},{"content":"\n                <label for=\"resp792682_2374978\">\n                    <span class=\"under_an\">C</span>. C3H8                </label>\n            ","id":"resp792682_2374978","value":"2374978"},{"content":"\n                <label for=\"resp792682_2374980\">\n                    <span class=\"under_an\">D</span>. C3H9N                </label>\n            ","id":"resp792682_2374980","value":"2374980"}]},{"content":"\n    Số amin ứng với công thức phân tử C4H11N mà khi cho vào dung dịch HNO2 không có khí bay ra là","info":"\n\t10.\n      ","answers":[{"content":"\n                <label for=\"resp792684_2374982\">\n                    <span class=\"under_an\">A</span>. 3                </label>\n            ","id":"resp792684_2374982","value":"2374982"},{"content":"\n                <label for=\"resp792684_2374984\">\n                    <span class=\"under_an\">B</span>. 2                </label>\n            ","id":"resp792684_2374984","value":"2374984"},{"content":"\n                <label for=\"resp792684_2374986\">\n                    <span class=\"under_an\">C</span>. 5                </label>\n            ","id":"resp792684_2374986","value":"2374986"},{"content":"\n                <label for=\"resp792684_2374988\">\n                    <span class=\"under_an\">D</span>. 4                </label>\n            ","id":"resp792684_2374988","value":"2374988"}]},{"content":"\n    Phát biểu nào dưới đây không đúng?","info":"\n\t11.\n      ","answers":[{"content":"\n                <label for=\"resp792686_2374990\">\n                    <span class=\"under_an\">A</span>. Propan-2-amin (isopropyl amin) là một amin bậc hai                </label>\n            ","id":"resp792686_2374990","value":"2374990"},{"content":"\n                <label for=\"resp792686_2374992\">\n                    <span class=\"under_an\">B</span>. Tên gọi thông dụng của benzen amin (phenyl amin) là anilin.                </label>\n            ","id":"resp792686_2374992","value":"2374992"},{"content":"\n                <label for=\"resp792686_2374994\">\n                    <span class=\"under_an\">C</span>. Có bốn đồng phân cấu tạo amin có cùng công thức phân tử C3H9N.                </label>\n            ","id":"resp792686_2374994","value":"2374994"},{"content":"\n                <label for=\"resp792686_2374996\">\n                    <span class=\"under_an\">D</span>. Dãy đồng đẳng amin no, đơn chức , mạch hở có công thức CnH2n+3N.                </label>\n            ","id":"resp792686_2374996","value":"2374996"}]},{"content":"\n    Chất nào dưới đây là chất rắn không màu, dễ tan trong nước, kết tinh ở điều kiện thường?","info":"\n\t12.\n      ","answers":[{"content":"\n                <label for=\"resp792688_2374998\">\n                    <span class=\"under_an\">A</span>. C6H5NH2                </label>\n            ","id":"resp792688_2374998","value":"2374998"},{"content":"\n                <label for=\"resp792688_2375000\">\n                    <span class=\"under_an\">B</span>. C2H5OH                </label>\n            ","id":"resp792688_2375000","value":"2375000"},{"content":"\n                <label for=\"resp792688_2375002\">\n                    <span class=\"under_an\">C</span>. H2NCH2COOH                </label>\n            ","id":"resp792688_2375002","value":"2375002"},{"content":"\n                <label for=\"resp792688_2375004\">\n                    <span class=\"under_an\">D</span>. CH3NH2.                </label>\n            ","id":"resp792688_2375004","value":"2375004"}]},{"content":"\n    Alanin có công thức là","info":"\n\t13.\n      ","answers":[{"content":"\n                <label for=\"resp792690_2375006\">\n                    <span class=\"under_an\">A</span>. C6H5-NH2                </label>\n            ","id":"resp792690_2375006","value":"2375006"},{"content":"\n                <label for=\"resp792690_2375008\">\n                    <span class=\"under_an\">B</span>. CH3-CH(NH2)-COOH                </label>\n            ","id":"resp792690_2375008","value":"2375008"},{"content":"\n                <label for=\"resp792690_2375010\">\n                    <span class=\"under_an\">C</span>. H2N-CH2-COOH                </label>\n            ","id":"resp792690_2375010","value":"2375010"},{"content":"\n                <label for=\"resp792690_2375012\">\n                    <span class=\"under_an\">D</span>. H2N-CH2-CH2-COOH                </label>\n            ","id":"resp792690_2375012","value":"2375012"}]},{"content":"\n    Dãy chỉ chứa những amino axit có số nhóm amino và số nhóm cacboxyl bằng nhau là","info":"\n\t14.\n      ","answers":[{"content":"\n                <label for=\"resp792692_2375014\">\n                    <span class=\"under_an\">A</span>. Gly, Glu, Lys                </label>\n            ","id":"resp792692_2375014","value":"2375014"},{"content":"\n                <label for=\"resp792692_2375016\">\n                    <span class=\"under_an\">B</span>. Gly, Val, Ala                </label>\n            ","id":"resp792692_2375016","value":"2375016"},{"content":"\n                <label for=\"resp792692_2375018\">\n                    <span class=\"under_an\">C</span>. Val , Lys, Ala                </label>\n            ","id":"resp792692_2375018","value":"2375018"},{"content":"\n                <label for=\"resp792692_2375020\">\n                    <span class=\"under_an\">D</span>. Gly, Ala, Glu                </label>\n            ","id":"resp792692_2375020","value":"2375020"}]},{"content":"\n    Dãy chỉ chứa những amino axit có số nhóm amino và số nhóm cacboxyl bằng nhau là:","info":"\n\t15.\n      ","answers":[{"content":"\n                <label for=\"resp792694_2375022\">\n                    <span class=\"under_an\">A</span>. Gly, Ala, Glu, Tyr                </label>\n            ","id":"resp792694_2375022","value":"2375022"},{"content":"\n                <label for=\"resp792694_2375024\">\n                    <span class=\"under_an\">B</span>. Gly, Val, Lys, Ala.                </label>\n            ","id":"resp792694_2375024","value":"2375024"},{"content":"\n                <label for=\"resp792694_2375026\">\n                    <span class=\"under_an\">C</span>. Gly, Ala, Glu, Lys.                </label>\n            ","id":"resp792694_2375026","value":"2375026"},{"content":"\n                <label for=\"resp792694_2375028\">\n                    <span class=\"under_an\">D</span>. Gly, Val, Tyr, Ala                </label>\n            ","id":"resp792694_2375028","value":"2375028"}]},{"content":"\n    Hai hợp chất hữu cơ X và Y có cùng công thức phân tử là C3H7NO2, đều là chất rắn ở điều kiện thường. Chất X phản ứng với dung dịch NaOH, giải phóng khí. Chất Y có phản ứng trùng ngưng. Các chất X và Y lần lượt là ","info":"\n\t16.\n      ","answers":[{"content":"\n                <label for=\"resp792696_2375030\">\n                    <span class=\"under_an\">A</span>. amoni acrylat và axit 2-aminopropionic                </label>\n            ","id":"resp792696_2375030","value":"2375030"},{"content":"\n                <label for=\"resp792696_2375032\">\n                    <span class=\"under_an\">B</span>. axit 2-aminopropionic và amoni acrylat.                </label>\n            ","id":"resp792696_2375032","value":"2375032"},{"content":"\n                <label for=\"resp792696_2375034\">\n                    <span class=\"under_an\">C</span>. vinylamoni fomat và amoni acrylat.                </label>\n            ","id":"resp792696_2375034","value":"2375034"},{"content":"\n                <label for=\"resp792696_2375036\">\n                    <span class=\"under_an\">D</span>. axit 2-aminopropionic và axit 3-aminopropionic.                </label>\n            ","id":"resp792696_2375036","value":"2375036"}]},{"content":"\n    Tơ nitron dai, bền với nhiệt và giữ nhiệt tốt nên thường được dùng để dệt vải may quần áo ấm hoặc bện thành sợi “len” đan áo rét. Tơ nitron được tổng hợp từ monome nào sau đây?","info":"\n\t17.\n      ","answers":[{"content":"\n                <label for=\"resp792698_2375038\">\n                    <span class=\"under_an\">A</span>. Axit ε-aminocaproic                </label>\n            ","id":"resp792698_2375038","value":"2375038"},{"content":"\n                <label for=\"resp792698_2375040\">\n                    <span class=\"under_an\">B</span>. Vinyl Clorua                </label>\n            ","id":"resp792698_2375040","value":"2375040"},{"content":"\n                <label for=\"resp792698_2375042\">\n                    <span class=\"under_an\">C</span>. Caprolaclam                </label>\n            ","id":"resp792698_2375042","value":"2375042"},{"content":"\n                <label for=\"resp792698_2375044\">\n                    <span class=\"under_an\">D</span>. Acrilonitrin                </label>\n            ","id":"resp792698_2375044","value":"2375044"}]},{"content":"\n    Polime nào sau đây được dùng để chế tạo thủy tinh hữu cơ plexiglas?","info":"\n\t18.\n      ","answers":[{"content":"\n                <label for=\"resp792700_2375046\">\n                    <span class=\"under_an\">A</span>. Poli(vinyl clorua).                </label>\n            ","id":"resp792700_2375046","value":"2375046"},{"content":"\n                <label for=\"resp792700_2375048\">\n                    <span class=\"under_an\">B</span>. Polietilen                </label>\n            ","id":"resp792700_2375048","value":"2375048"},{"content":"\n                <label for=\"resp792700_2375050\">\n                    <span class=\"under_an\">C</span>. Poli(metyl metacrylat).                </label>\n            ","id":"resp792700_2375050","value":"2375050"},{"content":"\n                <label for=\"resp792700_2375052\">\n                    <span class=\"under_an\">D</span>. Poliacrilonitrin.                </label>\n            ","id":"resp792700_2375052","value":"2375052"}]},{"content":"\n    Dãy gồm các polime có cấu trúc mạch phân nhánh là","info":"\n\t19.\n      ","answers":[{"content":"\n                <label for=\"resp792702_2375054\">\n                    <span class=\"under_an\">A</span>. amilopectin, glicogen, poli(metyl metacrylat).                </label>\n            ","id":"resp792702_2375054","value":"2375054"},{"content":"\n                <label for=\"resp792702_2375056\">\n                    <span class=\"under_an\">B</span>. amilopectin, glicogen.                </label>\n            ","id":"resp792702_2375056","value":"2375056"},{"content":"\n                <label for=\"resp792702_2375058\">\n                    <span class=\"under_an\">C</span>. tơ visco, amilopectin, poli isopren.                </label>\n            ","id":"resp792702_2375058","value":"2375058"},{"content":"\n                <label for=\"resp792702_2375060\">\n                    <span class=\"under_an\">D</span>. nhựa novolac, tơ nitron, poli(vinyl clorua).                </label>\n            ","id":"resp792702_2375060","value":"2375060"}]},{"content":"\n    Dãy các chất đều có khả năng tham gia phản ứng thủy phân trong dung dịch H2SO4 loãng, nóng là","info":"\n\t20.\n      ","answers":[{"content":"\n                <label for=\"resp792704_2375062\">\n                    <span class=\"under_an\">A</span>. xenlulozơ, poli(vinyl clorua), nilon-7.                </label>\n            ","id":"resp792704_2375062","value":"2375062"},{"content":"\n                <label for=\"resp792704_2375064\">\n                    <span class=\"under_an\">B</span>. polistiren, amilopectin, poliacrilonitrin.                </label>\n            ","id":"resp792704_2375064","value":"2375064"},{"content":"\n                <label for=\"resp792704_2375066\">\n                    <span class=\"under_an\">C</span>. tơ lapsan, tơ axetat, polietilen.                </label>\n            ","id":"resp792704_2375066","value":"2375066"},{"content":"\n                <label for=\"resp792704_2375068\">\n                    <span class=\"under_an\">D</span>. nilon-6,6, nilon-6, amilozơ.                </label>\n            ","id":"resp792704_2375068","value":"2375068"}]}]},{"tag":{"title":"Kiểm tra môn Luyện thi 5+ môn Tiếng Anh - HOCMAI"},"title":"Bài tập tự luyện","subtitle":"ĐỀ KIỂM TRA ĐẦU VÀO KHÓA LUYỆN THI 5+","questions":[{"content":"\n    Mark the letter A, B, C or D on your sheet to indicate the correct answer to each of the following questions.\n Nobody took any _____ of the warning and they went swimming in the contaminated water.","info":"\n\t1.\n      ","answers":[{"content":"\n                <label for=\"resp792806_2375468\">\n                    <span class=\"under_an\">A</span>. notice                </label>\n            ","id":"resp792806_2375468","value":"2375468"},{"content":"\n                <label for=\"resp792806_2375462\">\n                    <span class=\"under_an\">B</span>. sight                </label>\n            ","id":"resp792806_2375462","value":"2375462"},{"content":"\n                <label for=\"resp792806_2375464\">\n                    <span class=\"under_an\">C</span>. attention                </label>\n            ","id":"resp792806_2375464","value":"2375464"},{"content":"\n                <label for=\"resp792806_2375466\">\n                    <span class=\"under_an\">D</span>. information                </label>\n            ","id":"resp792806_2375466","value":"2375466"}]},{"content":"\n    Mark the letter A, B, C or D on your sheet to indicate the correct answer to each of the following questions.\n My mother takes responsibility ______ running the household.","info":"\n\t2.\n      ","answers":[{"content":"\n                <label for=\"resp792794_2375420\">\n                    <span class=\"under_an\">A</span>. for                </label>\n            ","id":"resp792794_2375420","value":"2375420"},{"content":"\n                <label for=\"resp792794_2375416\">\n                    <span class=\"under_an\">B</span>. with                </label>\n            ","id":"resp792794_2375416","value":"2375416"},{"content":"\n                <label for=\"resp792794_2375418\">\n                    <span class=\"under_an\">C</span>. at                </label>\n            ","id":"resp792794_2375418","value":"2375418"},{"content":"\n                <label for=\"resp792794_2375414\">\n                    <span class=\"under_an\">D</span>. about                </label>\n            ","id":"resp792794_2375414","value":"2375414"}]},{"content":"\n    Mark the letter A, B, C or D on your sheet to indicate the correct answer to each of the following questions.\n Vietnamese children are taught at a very young age to obey and look _____ elderly people.","info":"\n\t3.\n      ","answers":[{"content":"\n                <label for=\"resp792800_2375440\">\n                    <span class=\"under_an\">A</span>. down on                </label>\n            ","id":"resp792800_2375440","value":"2375440"},{"content":"\n                <label for=\"resp792800_2375442\">\n                    <span class=\"under_an\">B</span>. away from                </label>\n            ","id":"resp792800_2375442","value":"2375442"},{"content":"\n                <label for=\"resp792800_2375438\">\n                    <span class=\"under_an\">C</span>. up to                </label>\n            ","id":"resp792800_2375438","value":"2375438"},{"content":"\n                <label for=\"resp792800_2375444\">\n                    <span class=\"under_an\">D</span>. out of                </label>\n            ","id":"resp792800_2375444","value":"2375444"}]},{"content":"\n    Mark the letter A, B, C or D on your sheet to indicate the correct answer to each of the following questions.\n ______ New York is not the capital of the USA, it is the home of the United Nations.","info":"\n\t4.\n      ","answers":[{"content":"\n                <label for=\"resp792816_2375506\">\n                    <span class=\"under_an\">A</span>. Otherwise                </label>\n            ","id":"resp792816_2375506","value":"2375506"},{"content":"\n                <label for=\"resp792816_2375508\">\n                    <span class=\"under_an\">B</span>. In spite of                </label>\n            ","id":"resp792816_2375508","value":"2375508"},{"content":"\n                <label for=\"resp792816_2375502\">\n                    <span class=\"under_an\">C</span>. Because                </label>\n            ","id":"resp792816_2375502","value":"2375502"},{"content":"\n                <label for=\"resp792816_2375504\">\n                    <span class=\"under_an\">D</span>. Although                </label>\n            ","id":"resp792816_2375504","value":"2375504"}]},{"content":"\n    Mark the letter A, B, C or D on your sheet to indicate the correct answer to each of the following questions.\n John cannot make a ______ to get married to Mary or stay single until he can afford a house and a car.","info":"\n\t5.\n      ","answers":[{"content":"\n                <label for=\"resp792812_2375488\">\n                    <span class=\"under_an\">A</span>. decide                </label>\n            ","id":"resp792812_2375488","value":"2375488"},{"content":"\n                <label for=\"resp792812_2375490\">\n                    <span class=\"under_an\">B</span>. decisively                </label>\n            ","id":"resp792812_2375490","value":"2375490"},{"content":"\n                <label for=\"resp792812_2375492\">\n                    <span class=\"under_an\">C</span>. decision                </label>\n            ","id":"resp792812_2375492","value":"2375492"},{"content":"\n                <label for=\"resp792812_2375486\">\n                    <span class=\"under_an\">D</span>. decisive                </label>\n            ","id":"resp792812_2375486","value":"2375486"}]},{"content":"\n    Mark the letter A, B, C or D on your sheet to indicate the correct answer to each of the following questions.\n Not only _______ in the field of psychology but animal behavior is examined as well.","info":"\n\t6.\n      ","answers":[{"content":"\n                <label for=\"resp792826_2375546\">\n                    <span class=\"under_an\">A</span>. human behavior                </label>\n            ","id":"resp792826_2375546","value":"2375546"},{"content":"\n                <label for=\"resp792826_2375542\">\n                    <span class=\"under_an\">B</span>. is human behavior studied                </label>\n            ","id":"resp792826_2375542","value":"2375542"},{"content":"\n                <label for=\"resp792826_2375548\">\n                    <span class=\"under_an\">C</span>. human behavior is studied                </label>\n            ","id":"resp792826_2375548","value":"2375548"},{"content":"\n                <label for=\"resp792826_2375544\">\n                    <span class=\"under_an\">D</span>. is studied human behavior                </label>\n            ","id":"resp792826_2375544","value":"2375544"}]},{"content":"\n    Mark the letter A, B, C or D on your sheet to indicate the correct answer to each of the following questions.\n According to FAO, Vietnam is ______ second largest coffee producer in the world.","info":"\n\t7.\n      ","answers":[{"content":"\n                <label for=\"resp792802_2375448\">\n                    <span class=\"under_an\">A</span>. a                </label>\n            ","id":"resp792802_2375448","value":"2375448"},{"content":"\n                <label for=\"resp792802_2375452\">\n                    <span class=\"under_an\">B</span>. O                </label>\n            ","id":"resp792802_2375452","value":"2375452"},{"content":"\n                <label for=\"resp792802_2375450\">\n                    <span class=\"under_an\">C</span>. the                </label>\n            ","id":"resp792802_2375450","value":"2375450"},{"content":"\n                <label for=\"resp792802_2375446\">\n                    <span class=\"under_an\">D</span>. an                </label>\n            ","id":"resp792802_2375446","value":"2375446"}]},{"content":"\n    Mark the letter A, B, C or D on your sheet to indicate the correct answer to each of the following questions.\n Tom visited us to come to his party, ______?","info":"\n\t8.\n      ","answers":[{"content":"\n                <label for=\"resp792810_2375482\">\n                    <span class=\"under_an\">A</span>. hadn’t he                </label>\n            ","id":"resp792810_2375482","value":"2375482"},{"content":"\n                <label for=\"resp792810_2375484\">\n                    <span class=\"under_an\">B</span>. didn’t he                </label>\n            ","id":"resp792810_2375484","value":"2375484"},{"content":"\n                <label for=\"resp792810_2375478\">\n                    <span class=\"under_an\">C</span>. couldn’t he                </label>\n            ","id":"resp792810_2375478","value":"2375478"},{"content":"\n                <label for=\"resp792810_2375480\">\n                    <span class=\"under_an\">D</span>. wasn’t he                </label>\n            ","id":"resp792810_2375480","value":"2375480"}]},{"content":"\n    Mark the letter A, B, C or D on your sheet to indicate the correct answer to each of the following questions.\n Last summer, we _____ to travel to Phu Quoc, which is considered the pearl island of Vietnam.","info":"\n\t9.\n      ","answers":[{"content":"\n                <label for=\"resp792814_2375494\">\n                    <span class=\"under_an\">A</span>. don’t mind                </label>\n            ","id":"resp792814_2375494","value":"2375494"},{"content":"\n                <label for=\"resp792814_2375496\">\n                    <span class=\"under_an\">B</span>. suggested                </label>\n            ","id":"resp792814_2375496","value":"2375496"},{"content":"\n                <label for=\"resp792814_2375498\">\n                    <span class=\"under_an\">C</span>. enjoyed                </label>\n            ","id":"resp792814_2375498","value":"2375498"},{"content":"\n                <label for=\"resp792814_2375500\">\n                    <span class=\"under_an\">D</span>. decided                </label>\n            ","id":"resp792814_2375500","value":"2375500"}]},{"content":"\n    Mark the letter A, B, C or D on your sheet to indicate the correct answer to each of the following questions.\n I must thank the man from _____ I got the present.","info":"\n\t10.\n      ","answers":[{"content":"\n                <label for=\"resp792798_2375434\">\n                    <span class=\"under_an\">A</span>. who                </label>\n            ","id":"resp792798_2375434","value":"2375434"},{"content":"\n                <label for=\"resp792798_2375430\">\n                    <span class=\"under_an\">B</span>. that                </label>\n            ","id":"resp792798_2375430","value":"2375430"},{"content":"\n                <label for=\"resp792798_2375432\">\n                    <span class=\"under_an\">C</span>. which                </label>\n            ","id":"resp792798_2375432","value":"2375432"},{"content":"\n                <label for=\"resp792798_2375436\">\n                    <span class=\"under_an\">D</span>. whom                </label>\n            ","id":"resp792798_2375436","value":"2375436"}]},{"content":"\n    Mark the letter A, B, C or D on your sheet to indicate the correct answer to each of the following questions.\n Only after she ______ from a severe illness did she realise the importance of good health.","info":"\n\t11.\n      ","answers":[{"content":"\n                <label for=\"resp792824_2375536\">\n                    <span class=\"under_an\">A</span>. has recovered                </label>\n            ","id":"resp792824_2375536","value":"2375536"},{"content":"\n                <label for=\"resp792824_2375540\">\n                    <span class=\"under_an\">B</span>. was recovering                </label>\n            ","id":"resp792824_2375540","value":"2375540"},{"content":"\n                <label for=\"resp792824_2375534\">\n                    <span class=\"under_an\">C</span>. would recover                </label>\n            ","id":"resp792824_2375534","value":"2375534"},{"content":"\n                <label for=\"resp792824_2375538\">\n                    <span class=\"under_an\">D</span>. had recovered                </label>\n            ","id":"resp792824_2375538","value":"2375538"}]},{"content":"\n    Mark the letter A, B, C or D on your sheet to indicate the correct answer to each of the following questions.\n I think the ______ thing to do is to phone before you go and ask for directions.","info":"\n\t12.\n      ","answers":[{"content":"\n                <label for=\"resp792804_2375454\">\n                    <span class=\"under_an\">A</span>. sensible                </label>\n            ","id":"resp792804_2375454","value":"2375454"},{"content":"\n                <label for=\"resp792804_2375458\">\n                    <span class=\"under_an\">B</span>. sensibly                </label>\n            ","id":"resp792804_2375458","value":"2375458"},{"content":"\n                <label for=\"resp792804_2375460\">\n                    <span class=\"under_an\">C</span>. sense                </label>\n            ","id":"resp792804_2375460","value":"2375460"},{"content":"\n                <label for=\"resp792804_2375456\">\n                    <span class=\"under_an\">D</span>. sensibility                </label>\n            ","id":"resp792804_2375456","value":"2375456"}]},{"content":"\n    Mark the letter A, B, C or D on your answer sheet to indicate the word whose underlined part differs from the other three in pronunciation in each of the following questions.","info":"\n\t13.\n      ","answers":[{"content":"\n                <label for=\"resp792788_2375392\">\n                    <span class=\"under_an\">A</span>. abolish<u>ed </u>                </label>\n            ","id":"resp792788_2375392","value":"2375392"},{"content":"\n                <label for=\"resp792788_2375390\">\n                    <span class=\"under_an\">B</span>. impress<u>ed </u>                </label>\n            ","id":"resp792788_2375390","value":"2375390"},{"content":"\n                <label for=\"resp792788_2375394\">\n                    <span class=\"under_an\">C</span>. influenc<u>ed </u>                </label>\n            ","id":"resp792788_2375394","value":"2375394"},{"content":"\n                <label for=\"resp792788_2375396\">\n                    <span class=\"under_an\">D</span>. heighten<u>ed </u>                </label>\n            ","id":"resp792788_2375396","value":"2375396"}]},{"content":"\n    Mark the letter A, B, C or D on your sheet to indicate the correct answer to each of the following questions.\n He wanted to know _______.","info":"\n\t14.\n      ","answers":[{"content":"\n                <label for=\"resp792822_2375528\">\n                    <span class=\"under_an\">A</span>. where he can change some money                </label>\n            ","id":"resp792822_2375528","value":"2375528"},{"content":"\n                <label for=\"resp792822_2375530\">\n                    <span class=\"under_an\">B</span>. where he could change some money                </label>\n            ","id":"resp792822_2375530","value":"2375530"},{"content":"\n                <label for=\"resp792822_2375532\">\n                    <span class=\"under_an\">C</span>. where could he change some money                </label>\n            ","id":"resp792822_2375532","value":"2375532"},{"content":"\n                <label for=\"resp792822_2375526\">\n                    <span class=\"under_an\">D</span>. where can he change some money                </label>\n            ","id":"resp792822_2375526","value":"2375526"}]},{"content":"\n    Mark the letter A, B, C or D on your sheet to indicate the correct answer to each of the following questions.\n Britain has accused Russia ______ poisoning the ex-Russian spy Sergei Skripal and his daughter.","info":"\n\t15.\n      ","answers":[{"content":"\n                <label for=\"resp792820_2375520\">\n                    <span class=\"under_an\">A</span>. from                </label>\n            ","id":"resp792820_2375520","value":"2375520"},{"content":"\n                <label for=\"resp792820_2375524\">\n                    <span class=\"under_an\">B</span>. on                </label>\n            ","id":"resp792820_2375524","value":"2375524"},{"content":"\n                <label for=\"resp792820_2375518\">\n                    <span class=\"under_an\">C</span>. of                </label>\n            ","id":"resp792820_2375518","value":"2375518"},{"content":"\n                <label for=\"resp792820_2375522\">\n                    <span class=\"under_an\">D</span>. for                </label>\n            ","id":"resp792820_2375522","value":"2375522"}]},{"content":"\n    Mark the letter A, B, C or D on your sheet to indicate the correct answer to each of the following questions.\n When I came to visit her last night, she ______ a bath.","info":"\n\t16.\n      ","answers":[{"content":"\n                <label for=\"resp792796_2375422\">\n                    <span class=\"under_an\">A</span>. had                </label>\n            ","id":"resp792796_2375422","value":"2375422"},{"content":"\n                <label for=\"resp792796_2375424\">\n                    <span class=\"under_an\">B</span>. has                </label>\n            ","id":"resp792796_2375424","value":"2375424"},{"content":"\n                <label for=\"resp792796_2375426\">\n                    <span class=\"under_an\">C</span>. is having                </label>\n            ","id":"resp792796_2375426","value":"2375426"},{"content":"\n                <label for=\"resp792796_2375428\">\n                    <span class=\"under_an\">D</span>. was having                </label>\n            ","id":"resp792796_2375428","value":"2375428"}]},{"content":"\n    Mark the letter A, B, C or D on your sheet to indicate the correct answer to each of the following questions.\n Kathy is a very ______ girl. She can make friends easily even though she is in a strange place.","info":"\n\t17.\n      ","answers":[{"content":"\n                <label for=\"resp792818_2375512\">\n                    <span class=\"under_an\">A</span>. polite                </label>\n            ","id":"resp792818_2375512","value":"2375512"},{"content":"\n                <label for=\"resp792818_2375514\">\n                    <span class=\"under_an\">B</span>. sociable                </label>\n            ","id":"resp792818_2375514","value":"2375514"},{"content":"\n                <label for=\"resp792818_2375516\">\n                    <span class=\"under_an\">C</span>. unfriendly                </label>\n            ","id":"resp792818_2375516","value":"2375516"},{"content":"\n                <label for=\"resp792818_2375510\">\n                    <span class=\"under_an\">D</span>. shy                </label>\n            ","id":"resp792818_2375510","value":"2375510"}]},{"content":"\n    Mark the letter A, B, C or D on your sheet to indicate the indicate the sentence that best completes each of the following exchanges.\n - “Do you mind if I take a seat?” – “ ______”","info":"\n\t18.\n      ","answers":[{"content":"\n                <label for=\"resp792792_2375410\">\n                    <span class=\"under_an\">A</span>. Yes, do as you please                </label>\n            ","id":"resp792792_2375410","value":"2375410"},{"content":"\n                <label for=\"resp792792_2375408\">\n                    <span class=\"under_an\">B</span>. No, do as you please                </label>\n            ","id":"resp792792_2375408","value":"2375408"},{"content":"\n                <label for=\"resp792792_2375412\">\n                    <span class=\"under_an\">C</span>. Yes, I don’t mind                </label>\n            ","id":"resp792792_2375412","value":"2375412"},{"content":"\n                <label for=\"resp792792_2375406\">\n                    <span class=\"under_an\">D</span>. No I mind                </label>\n            ","id":"resp792792_2375406","value":"2375406"}]},{"content":"\n    Mark the letter A, B, C or D on your answer sheet to indicate the word that differs from the other three in the position of the primary stress in each of the following questions.","info":"\n\t19.\n      ","answers":[{"content":"\n                <label for=\"resp792790_2375402\">\n                    <span class=\"under_an\">A</span>. postcard                </label>\n            ","id":"resp792790_2375402","value":"2375402"},{"content":"\n                <label for=\"resp792790_2375398\">\n                    <span class=\"under_an\">B</span>. measure                </label>\n            ","id":"resp792790_2375398","value":"2375398"},{"content":"\n                <label for=\"resp792790_2375400\">\n                    <span class=\"under_an\">C</span>. context                </label>\n            ","id":"resp792790_2375400","value":"2375400"},{"content":"\n                <label for=\"resp792790_2375404\">\n                    <span class=\"under_an\">D</span>. resource                </label>\n            ","id":"resp792790_2375404","value":"2375404"}]},{"content":"\n    Mark the letter A, B, C or D on your sheet to indicate the correct answer to each of the following questions.\n If the firemen hadn’t arrived in time, the fire _____ to other houses.","info":"\n\t20.\n      ","answers":[{"content":"\n                <label for=\"resp792808_2375474\">\n                    <span class=\"under_an\">A</span>. would have spread                </label>\n            ","id":"resp792808_2375474","value":"2375474"},{"content":"\n                <label for=\"resp792808_2375476\">\n                    <span class=\"under_an\">B</span>. will spread                </label>\n            ","id":"resp792808_2375476","value":"2375476"},{"content":"\n                <label for=\"resp792808_2375472\">\n                    <span class=\"under_an\">C</span>. had spread                </label>\n            ","id":"resp792808_2375472","value":"2375472"},{"content":"\n                <label for=\"resp792808_2375470\">\n                    <span class=\"under_an\">D</span>. would spread                </label>\n            ","id":"resp792808_2375470","value":"2375470"}]}]}]