[{"tag":{"title":"Kiểm tra môn Hóa học - HOCMAI"},"title":"Bài tập tự luyện","subtitle":"Đề kiểm tra đầu vào PEN-C (2018-2019) - Dành cho học sinh lớp 12","questions":[{"content":"\n    Hấp thụ hoàn toàn 2,688 lit khí CO2 (đktc) vào 2,5 lit dung dịch Ba(OH)2 a mol/l thu được 15,76g kết tủa. Giá trị của a là:\n","info":"\n\t1.\n      ","answers":[{"content":"\n                <label for=\"resp121162_365784\">\n                    <span class=\"under_an\">A</span>. 0,048                </label>\n            ","id":"resp121162_365784","value":"365784"},{"content":"\n                <label for=\"resp121162_365783\">\n                    <span class=\"under_an\">B</span>. 0,032                </label>\n            ","id":"resp121162_365783","value":"365783"},{"content":"\n                <label for=\"resp121162_365786\">\n                    <span class=\"under_an\">C</span>. 0,04                </label>\n            ","id":"resp121162_365786","value":"365786"},{"content":"\n                <label for=\"resp121162_365785\">\n                    <span class=\"under_an\">D</span>. 0,06                </label>\n            ","id":"resp121162_365785","value":"365785"}]},{"content":"\n    Hỗn hợp X gồm \\[{{C}_{n}}{{H}_{2n-1}}CHO\\]; \\[{{C}_{n}}{{H}_{2n-2}}{{\\left( CHO \\right)}_{2}}\\]; \\[{{C}_{n}}{{H}_{2n-2}}{{\\left( COOH \\right)}_{2}}\\]; \\[{{C}_{n}}{{H}_{2n-3}}\\left( CHO \\right){{\\left( COOH \\right)}_{2}}\\]. Cho m gam hỗn hợp X tác dụng với dung dịch \\[AgN{{O}_{3}}/N{{H}_{3}}\\] dư thu được 56,16 gam kết tủa bạc. Trung hòa m gam hỗn hợp X cần dùng 30 gam dung dịch hỗn hợp NaOH 12% và KOH 5,6%. Đốt m gam hỗn hợp X cần dùng (m + 7,92) gam \\[{{O}_{2}}\\]. Giá trị gần nhất của m là","info":"\n\t2.\n      ","answers":[{"content":"\n                <label for=\"resp696146_2037983\">\n                    <span class=\"under_an\">A</span>. 20,0.                </label>\n            ","id":"resp696146_2037983","value":"2037983"},{"content":"\n                <label for=\"resp696146_2037982\">\n                    <span class=\"under_an\">B</span>. 19,0.                </label>\n            ","id":"resp696146_2037982","value":"2037982"},{"content":"\n                <label for=\"resp696146_2037985\">\n                    <span class=\"under_an\">C</span>. 18,5.                </label>\n            ","id":"resp696146_2037985","value":"2037985"},{"content":"\n                <label for=\"resp696146_2037984\">\n                    <span class=\"under_an\">D</span>. 19,5.                </label>\n            ","id":"resp696146_2037984","value":"2037984"}]},{"content":"\n    Hỗn hợp X gồm axit oxalic, axit axetic, axit acrylic và axit malonic (\\[HOOCC{{H}_{2}}COOH\\]). Cho 0,25 mol hỗn hợp X phản ứng hết với lượng dư dung dịch\\[NaHC{{O}_{3}}\\], thu được 0,4 mol\\[C{{O}_{2}}\\]. Đốt cháy hoàn toàn 0,25 mol X trên cần dùng vừa đủ 0,4 mol O2, thu được CO2 và 7,2 gam\\[{{H}_{2}}O\\]. Cho các phát biểu sau:\n (1) Trong X, axit acrylic tác dụng vừa đủ với 100 ml dung dịch \\[B{{r}_{2}}\\] 1M \n (2) Phần trăm khối lượng của axit oxalic trong X gần nhất với 43,27% \n (3) Trong X, axit malonic tác dụng với lượng dư kim loại Na sinh ra 3,36 lít khí (đktc) \n (4) Khối lượng của axit axetic trong X là 3,0 gam \nSố phát biểu đúng là: ","info":"\n\t3.\n      ","answers":[{"content":"\n                <label for=\"resp696053_2037613\">\n                    <span class=\"under_an\">A</span>. 4                </label>\n            ","id":"resp696053_2037613","value":"2037613"},{"content":"\n                <label for=\"resp696053_2037612\">\n                    <span class=\"under_an\">B</span>. 3                </label>\n            ","id":"resp696053_2037612","value":"2037612"},{"content":"\n                <label for=\"resp696053_2037610\">\n                    <span class=\"under_an\">C</span>. 1                </label>\n            ","id":"resp696053_2037610","value":"2037610"},{"content":"\n                <label for=\"resp696053_2037611\">\n                    <span class=\"under_an\">D</span>. 2                </label>\n            ","id":"resp696053_2037611","value":"2037611"}]},{"content":"\n    Cho 44 g dung dịch NaOH 10% tác dụng với 10 g dung dịch axit photphoric 39,2%. Muối nào sau đây thu được phản ứng? ","info":"\n\t4.\n      ","answers":[{"content":"\n                <label for=\"resp78074_257486\">\n                    <span class=\"under_an\">A</span>. Na<sub>3</sub>PO<sub>4</sub>, và Na<sub>2</sub>HPO<sub>4</sub>                </label>\n            ","id":"resp78074_257486","value":"257486"},{"content":"\n                <label for=\"resp78074_257483\">\n                    <span class=\"under_an\">B</span>. Na<sub>2</sub>HPO<sub>4</sub>                </label>\n            ","id":"resp78074_257483","value":"257483"},{"content":"\n                <label for=\"resp78074_257484\">\n                    <span class=\"under_an\">C</span>. NaH<sub>2</sub>PO<sub>4</sub>                </label>\n            ","id":"resp78074_257484","value":"257484"},{"content":"\n                <label for=\"resp78074_257485\">\n                    <span class=\"under_an\">D</span>. Na<sub>2</sub>HPO<sub>4</sub> và NaH<sub>2</sub>PO<sub>4</sub>                </label>\n            ","id":"resp78074_257485","value":"257485"}]},{"content":"\n    Ở trạng thái cơ bản, cấu hình electron của nguyên tử Na( Z = 11) là","info":"\n\t5.\n      ","answers":[{"content":"\n                <label for=\"resp645668_1864763\">\n                    <span class=\"under_an\">A</span>. 1s<sup>2</sup>2s<sup>2</sup>2p<sup>6</sup>3s<sup>2</sup>                </label>\n            ","id":"resp645668_1864763","value":"1864763"},{"content":"\n                <label for=\"resp645668_1864761\">\n                    <span class=\"under_an\">B</span>. 1s<sup>2</sup>2s<sup>2</sup>2p<sup>5</sup>3s<sup>2 </sup>                </label>\n            ","id":"resp645668_1864761","value":"1864761"},{"content":"\n                <label for=\"resp645668_1864764\">\n                    <span class=\"under_an\">C</span>. 1s<sup>2</sup>2s<sup>2</sup>2p<sup>6</sup>3s<sup>1 </sup>                </label>\n            ","id":"resp645668_1864764","value":"1864764"},{"content":"\n                <label for=\"resp645668_1864762\">\n                    <span class=\"under_an\">D</span>. 1s<sup>2</sup>2s<sup>2</sup>2p<sup>4</sup>3s<sup>1 </sup>                </label>\n            ","id":"resp645668_1864762","value":"1864762"}]},{"content":"\n    Clo có thể phản ứng được với tất cả các chất trong dãy nào sau đây ?","info":"\n\t6.\n      ","answers":[{"content":"\n                <label for=\"resp682744_1993038\">\n                    <span class=\"under_an\">A</span>. Fe, Cu, O<sub>2</sub> , N<sub>2</sub>.                </label>\n            ","id":"resp682744_1993038","value":"1993038"},{"content":"\n                <label for=\"resp682744_1993036\">\n                    <span class=\"under_an\">B</span>. NaBr, NaI, NaOH.                </label>\n            ","id":"resp682744_1993036","value":"1993036"},{"content":"\n                <label for=\"resp682744_1993037\">\n                    <span class=\"under_an\">C</span>. ZnO, Na<sub>2</sub>SO<sub>4</sub>, Ba(OH)<sub>2</sub>.                </label>\n            ","id":"resp682744_1993037","value":"1993037"},{"content":"\n                <label for=\"resp682744_1993035\">\n                    <span class=\"under_an\">D</span>. Cu, CuO, Ca(OH)<sub>2</sub>, AgNO<sub>3</sub>.                </label>\n            ","id":"resp682744_1993035","value":"1993035"}]},{"content":"\n    Cho 13 gam kẽm tác dụng với 3,2 gam lưu huỳnh sản phẩm thu được sau phản ứng là:","info":"\n\t7.\n      ","answers":[{"content":"\n                <label for=\"resp703240_2060896\">\n                    <span class=\"under_an\">A</span>. ZnS, Zn và S.                </label>\n            ","id":"resp703240_2060896","value":"2060896"},{"content":"\n                <label for=\"resp703240_2060892\">\n                    <span class=\"under_an\">B</span>. ZnS và S                </label>\n            ","id":"resp703240_2060892","value":"2060892"},{"content":"\n                <label for=\"resp703240_2060890\">\n                    <span class=\"under_an\">C</span>. ZnS                </label>\n            ","id":"resp703240_2060890","value":"2060890"},{"content":"\n                <label for=\"resp703240_2060894\">\n                    <span class=\"under_an\">D</span>. ZnS và Zn                </label>\n            ","id":"resp703240_2060894","value":"2060894"}]},{"content":"\n    Tổng hệ số của các chất trong phản ứng:\n \n \n \n \n \n \n Cu + HNO3 → Cu(NO3)2 + NO + H2O là","info":"\n\t8.\n      ","answers":[{"content":"\n                <label for=\"resp676183_1969171\">\n                    <span class=\"under_an\">A</span>. 20                </label>\n            ","id":"resp676183_1969171","value":"1969171"},{"content":"\n                <label for=\"resp676183_1969172\">\n                    <span class=\"under_an\">B</span>. 25                </label>\n            ","id":"resp676183_1969172","value":"1969172"},{"content":"\n                <label for=\"resp676183_1969173\">\n                    <span class=\"under_an\">C</span>. 50                </label>\n            ","id":"resp676183_1969173","value":"1969173"},{"content":"\n                <label for=\"resp676183_1969170\">\n                    <span class=\"under_an\">D</span>. 55                </label>\n            ","id":"resp676183_1969170","value":"1969170"}]},{"content":"\n    Tổng số hợp chất hữu cơ mạch hở, có cùng công thức phân tử \\[{{C}_{4}}{{H}_{8}}{{O}_{2}}\\], phản ứng được với dung dịch Na nhưng không có phản ứng tráng bạc là","info":"\n\t9.\n      ","answers":[{"content":"\n                <label for=\"resp696052_2037607\">\n                    <span class=\"under_an\">A</span>. 9.                </label>\n            ","id":"resp696052_2037607","value":"2037607"},{"content":"\n                <label for=\"resp696052_2037606\">\n                    <span class=\"under_an\">B</span>. 5.                </label>\n            ","id":"resp696052_2037606","value":"2037606"},{"content":"\n                <label for=\"resp696052_2037609\">\n                    <span class=\"under_an\">C</span>. 8.                </label>\n            ","id":"resp696052_2037609","value":"2037609"},{"content":"\n                <label for=\"resp696052_2037608\">\n                    <span class=\"under_an\">D</span>. 4.                </label>\n            ","id":"resp696052_2037608","value":"2037608"}]},{"content":"\n    Tổng hệ số của các chất trong phản ứng: Fe3O4 + HNO3 →Fe(NO3)3 + NO + H2O là","info":"\n\t10.\n      ","answers":[{"content":"\n                <label for=\"resp676182_1969167\">\n                    <span class=\"under_an\">A</span>. 20                </label>\n            ","id":"resp676182_1969167","value":"1969167"},{"content":"\n                <label for=\"resp676182_1969169\">\n                    <span class=\"under_an\">B</span>. 50                </label>\n            ","id":"resp676182_1969169","value":"1969169"},{"content":"\n                <label for=\"resp676182_1969166\">\n                    <span class=\"under_an\">C</span>. 55                </label>\n            ","id":"resp676182_1969166","value":"1969166"},{"content":"\n                <label for=\"resp676182_1969168\">\n                    <span class=\"under_an\">D</span>. 25                </label>\n            ","id":"resp676182_1969168","value":"1969168"}]},{"content":"\n    Dung dịch NaOH có nồng độ 0,001M, pH của dung dịch là ","info":"\n\t11.\n      ","answers":[{"content":"\n                <label for=\"resp83368_266970\">\n                    <span class=\"under_an\">A</span>. 3.                </label>\n            ","id":"resp83368_266970","value":"266970"},{"content":"\n                <label for=\"resp83368_266971\">\n                    <span class=\"under_an\">B</span>. 7.                </label>\n            ","id":"resp83368_266971","value":"266971"},{"content":"\n                <label for=\"resp83368_266972\">\n                    <span class=\"under_an\">C</span>. 11.                </label>\n            ","id":"resp83368_266972","value":"266972"},{"content":"\n                <label for=\"resp83368_266973\">\n                    <span class=\"under_an\">D</span>. 12.                </label>\n            ","id":"resp83368_266973","value":"266973"}]},{"content":"\n    Cho các hợp chất thơm: \n(1) $$p-HO-C{{H}_{2}}-{{C}_{6}}{{H}_{4}}-OH;$$\n(2) $$p-C{{H}_{3}}O-{{C}_{6}}{{H}_{4}}-OH$$; \n(3) $$p-HO-{{C}_{6}}{{H}_{4}}-COO{{C}_{2}}{{H}_{5}};$$ \n(4) $$p-HO-{{C}_{6}}{{H}_{4}}-COOH$$; \n(5) $$p-HCOO-{{C}_{6}}{{H}_{4}}-OH$$; \n(6) $$m-HO-{{C}_{6}}{{H}_{4}}-C{{H}_{2}}OH;$$. \nCó bao nhiêu chất trong dãy thỏa mãn đồng thời 2 điều kiện sau? \n (a) Tác dụng với NaOH theo tỉ lệ mol 1: 1 \n (b) Tác dụng với Na dư tạo ra số mol $${{H}_{2}}$$ bằng số mol chất phản ứng","info":"\n\t12.\n      ","answers":[{"content":"\n                <label for=\"resp717310_2111220\">\n                    <span class=\"under_an\">A</span>. 2                </label>\n            ","id":"resp717310_2111220","value":"2111220"},{"content":"\n                <label for=\"resp717310_2111224\">\n                    <span class=\"under_an\">B</span>. 4                </label>\n            ","id":"resp717310_2111224","value":"2111224"},{"content":"\n                <label for=\"resp717310_2111218\">\n                    <span class=\"under_an\">C</span>. 1                </label>\n            ","id":"resp717310_2111218","value":"2111218"},{"content":"\n                <label for=\"resp717310_2111222\">\n                    <span class=\"under_an\">D</span>. 3                </label>\n            ","id":"resp717310_2111222","value":"2111222"}]},{"content":"\n    Trong CN người ta điều chế NH3 theo phương trình hoá học:\n $${{N}_{2}}+3{{H}_{2}}\\rightleftarrows 2N{{H}_{3}}$$\n Khi tăng nồng độ H2 lên hai\n lần (giữ nguyên nồng độ của N2 và nhiệt độ phản ứng) thì tốc độ phản ứng tăng lên bao nhiêu lần?","info":"\n\t13.\n      ","answers":[{"content":"\n                <label for=\"resp708286_2079378\">\n                    <span class=\"under_an\">A</span>. 8 lần                </label>\n            ","id":"resp708286_2079378","value":"2079378"},{"content":"\n                <label for=\"resp708286_2079380\">\n                    <span class=\"under_an\">B</span>. 16 lần                </label>\n            ","id":"resp708286_2079380","value":"2079380"},{"content":"\n                <label for=\"resp708286_2079376\">\n                    <span class=\"under_an\">C</span>. 4 lần                </label>\n            ","id":"resp708286_2079376","value":"2079376"},{"content":"\n                <label for=\"resp708286_2079374\">\n                    <span class=\"under_an\">D</span>. 2 lần                </label>\n            ","id":"resp708286_2079374","value":"2079374"}]},{"content":"\n    Cho 4,48 lít khí CO (đktc) từ từ qua ống sứ nung nóng đựng 8g một oxit sắt đến khi phản ứng hoàn toàn. Khí thu được sau phản ứng có tỉ khối hơi so với hiđro là 20. Công thức oxit sắt và % thể tích CO2 trong hỗn hợp sau phản ứng là\n","info":"\n\t14.\n      ","answers":[{"content":"\n                <label for=\"resp121201_365842\">\n                    <span class=\"under_an\">A</span>. Fe<sub>3</sub>O<sub>4</sub>, 75%                </label>\n            ","id":"resp121201_365842","value":"365842"},{"content":"\n                <label for=\"resp121201_365841\">\n                    <span class=\"under_an\">B</span>. Fe<sub>2</sub>O<sub>3</sub>, 65%                </label>\n            ","id":"resp121201_365841","value":"365841"},{"content":"\n                <label for=\"resp121201_365840\">\n                    <span class=\"under_an\">C</span>. Fe<sub>2</sub>O<sub>3</sub>, 75%                </label>\n            ","id":"resp121201_365840","value":"365840"},{"content":"\n                <label for=\"resp121201_365839\">\n                    <span class=\"under_an\">D</span>. FeO, 75%                </label>\n            ","id":"resp121201_365839","value":"365839"}]},{"content":"\n    Đun nóng hỗn hợp khí X (gồm 0,01 mol buta -1,3- đien, 0,03 mol axetilen; 0,015 mol vinylaxetilen; 0,015 mol propen và 0,15 mol\\[{{H}_{2}}\\] ) trong một bình kín (xúc tác Ni), sau một thời gian thu được hỗn hợp khí Y. Cho Y tác dụng vừa đủ với 400 ml dung dịch brom 0,1M. Tỉ khối của Y so với \\[{{H}_{2}}\\] có giá trị gần nhất với:","info":"\n\t15.\n      ","answers":[{"content":"\n                <label for=\"resp696051_2037603\">\n                    <span class=\"under_an\">A</span>. 15,5                </label>\n            ","id":"resp696051_2037603","value":"2037603"},{"content":"\n                <label for=\"resp696051_2037602\">\n                    <span class=\"under_an\">B</span>. 12,5                </label>\n            ","id":"resp696051_2037602","value":"2037602"},{"content":"\n                <label for=\"resp696051_2037604\">\n                    <span class=\"under_an\">C</span>. 11,5                </label>\n            ","id":"resp696051_2037604","value":"2037604"},{"content":"\n                <label for=\"resp696051_2037605\">\n                    <span class=\"under_an\">D</span>. 13,5                </label>\n            ","id":"resp696051_2037605","value":"2037605"}]},{"content":"\n    Cho 17,6 g hỗn hợp Fe, Cu tác dụng với H2SO4đặc, nóng thu được 8,96 lít SO2(đktc). Khối lượng mỗi kim loại.","info":"\n\t16.\n      ","answers":[{"content":"\n                <label for=\"resp703452_2061738\">\n                    <span class=\"under_an\">A</span>. 11,2g và 6,4g                </label>\n            ","id":"resp703452_2061738","value":"2061738"},{"content":"\n                <label for=\"resp703452_2061744\">\n                    <span class=\"under_an\">B</span>. 8,4g và 9,2g                </label>\n            ","id":"resp703452_2061744","value":"2061744"},{"content":"\n                <label for=\"resp703452_2061740\">\n                    <span class=\"under_an\">C</span>. 15g và 2,6g                </label>\n            ","id":"resp703452_2061740","value":"2061740"},{"content":"\n                <label for=\"resp703452_2061742\">\n                    <span class=\"under_an\">D</span>. 5,6g và 12 g.                </label>\n            ","id":"resp703452_2061742","value":"2061742"}]},{"content":"\n    Cho 16 gam hỗn hợp bột Fe và Mg tác dụng với dung dịch HCl dư thấy có 1 gam khí H2 bay ra. Khối lượng muối clorua tạo ra trong dung dịch là bao nhiêu gam?","info":"\n\t17.\n      ","answers":[{"content":"\n                <label for=\"resp682717_1992928\">\n                    <span class=\"under_an\">A</span>. 51,5 gam.                </label>\n            ","id":"resp682717_1992928","value":"1992928"},{"content":"\n                <label for=\"resp682717_1992929\">\n                    <span class=\"under_an\">B</span>. 87 gam .                </label>\n            ","id":"resp682717_1992929","value":"1992929"},{"content":"\n                <label for=\"resp682717_1992927\">\n                    <span class=\"under_an\">C</span>. 33,75 gam.                </label>\n            ","id":"resp682717_1992927","value":"1992927"},{"content":"\n                <label for=\"resp682717_1992930\">\n                    <span class=\"under_an\">D</span>. kết quả khác.                </label>\n            ","id":"resp682717_1992930","value":"1992930"}]},{"content":"\n    Hiđroxit nào sau đây không phải hiđroxit lưỡng tính?","info":"\n\t18.\n      ","answers":[{"content":"\n                <label for=\"resp76659_254521\">\n                    <span class=\"under_an\">A</span>. Zn(OH)<sub>2</sub>                </label>\n            ","id":"resp76659_254521","value":"254521"},{"content":"\n                <label for=\"resp76659_254520\">\n                    <span class=\"under_an\">B</span>. Pb(OH)<sub>2</sub>                </label>\n            ","id":"resp76659_254520","value":"254520"},{"content":"\n                <label for=\"resp76659_254522\">\n                    <span class=\"under_an\">C</span>. Mg(OH)<sub>2</sub>                </label>\n            ","id":"resp76659_254522","value":"254522"},{"content":"\n                <label for=\"resp76659_254519\">\n                    <span class=\"under_an\">D</span>. Sn(OH)<sub>2</sub>                </label>\n            ","id":"resp76659_254519","value":"254519"}]},{"content":"\n    Hỗn hợp bột A gồm Al và Cu. Chia A làm 2 phần bằng nhau. - Hòa tan phần một bằng dung dịch HNO3 đặc nguội thu được 8,96 lít một khí duy nhất. - Hòa tan phần hai bằng dung dịch HCl dư thu được 6,72 lít khí . Các thể tích khí được đo ở đktc.Thành phần % về khối lượng của các kim loại trong hỗn hợp A là","info":"\n\t19.\n      ","answers":[{"content":"\n                <label for=\"resp84836_268683\">\n                    <span class=\"under_an\">A</span>. 29,67% Al và 70,33 % Cu.                </label>\n            ","id":"resp84836_268683","value":"268683"},{"content":"\n                <label for=\"resp84836_268685\">\n                    <span class=\"under_an\">B</span>. 70,33% Al và 29,67 % Cu.                </label>\n            ","id":"resp84836_268685","value":"268685"},{"content":"\n                <label for=\"resp84836_268684\">\n                    <span class=\"under_an\">C</span>. 45,76% Al và 54,24 % Cu.                </label>\n            ","id":"resp84836_268684","value":"268684"},{"content":"\n                <label for=\"resp84836_268686\">\n                    <span class=\"under_an\">D</span>. 54,24% Al và 45,76 % Cu.                </label>\n            ","id":"resp84836_268686","value":"268686"}]},{"content":"\n    Dẫn hỗn hợp X gồm 0,05 mol \\[{{C}_{2}}{{H}_{2}}\\]; 0,1 mol \\[{{C}_{3}}{{H}_{4}}\\] và 0,1 mol \\[{{H}_{2}}\\] qua ống chứa Ni nung nóng, thu được hỗn hợp khí Y gồm 7 chất. Đốt cháy hoàn toàn Y rồi cho sản phẩm cháy hấp thụ hết vào 700 ml dung dịch NaOH 1M, thu được dung dịch Z. Tổng khối lượng chất tan trong dung dịch Z là","info":"\n\t20.\n      ","answers":[{"content":"\n                <label for=\"resp696144_2037977\">\n                    <span class=\"under_an\">A</span>. 38,2                </label>\n            ","id":"resp696144_2037977","value":"2037977"},{"content":"\n                <label for=\"resp696144_2037976\">\n                    <span class=\"under_an\">B</span>. 40,2                </label>\n            ","id":"resp696144_2037976","value":"2037976"},{"content":"\n                <label for=\"resp696144_2037975\">\n                    <span class=\"under_an\">C</span>. 45,6                </label>\n            ","id":"resp696144_2037975","value":"2037975"},{"content":"\n                <label for=\"resp696144_2037974\">\n                    <span class=\"under_an\">D</span>. 35,8                </label>\n            ","id":"resp696144_2037974","value":"2037974"}]}]},{"tag":{"title":"Kiểm tra môn Hóa học - HOCMAI"},"title":"Bài tập tự luyện","subtitle":"Đề kiểm tra đầu vào PEN-C (2018-2019) - Dành cho học sinh lớp 13","questions":[{"content":"\n    Hỗn hợp X gồm metyl fomat, anđehit acrylic và metyl acrylat. Đốt cháy hoàn toàn m gam X rồi hấp thụ hết sản phẩm cháy vào dung dịch Ca(OH)2 dư, thu được 9 gam kết tủa và khối lượng dung dịch giảm 3,78 gam. Giá trị của m là","info":"\n\t1.\n      ","answers":[{"content":"\n                <label for=\"resp722616_2127980\">\n                    <span class=\"under_an\">A</span>. 1,95                </label>\n            ","id":"resp722616_2127980","value":"2127980"},{"content":"\n                <label for=\"resp722616_2127982\">\n                    <span class=\"under_an\">B</span>. 1,54                </label>\n            ","id":"resp722616_2127982","value":"2127982"},{"content":"\n                <label for=\"resp722616_2127984\">\n                    <span class=\"under_an\">C</span>. 1,22                </label>\n            ","id":"resp722616_2127984","value":"2127984"},{"content":"\n                <label for=\"resp722616_2127986\">\n                    <span class=\"under_an\">D</span>. 2,02                </label>\n            ","id":"resp722616_2127986","value":"2127986"}]},{"content":"\n    Đốt cháy hoàn toàn 14,24 gam hỗn hợp X chứa 2 este đều no, đơn chức, mạch hở thu được CO2 và H2O có tổng khối lượng là 34,72 gam. Mặt khác đun nóng 14,24 gam X với dung dịch NaOH vừa đủ, thu được hỗn hợp Y chứa 2 ancol kế tiếp và hỗn hợp Z chứa 2 muối của 2 axit cacboxylic kế tiếp, trong đó có a gam muối A và b gam muối B (MA < MB). Tỉ lệ gần nhất của a : b là","info":"\n\t2.\n      ","answers":[{"content":"\n                <label for=\"resp722618_2127836\">\n                    <span class=\"under_an\">A</span>. 0,6                </label>\n            ","id":"resp722618_2127836","value":"2127836"},{"content":"\n                <label for=\"resp722618_2127838\">\n                    <span class=\"under_an\">B</span>. 1,25                </label>\n            ","id":"resp722618_2127838","value":"2127838"},{"content":"\n                <label for=\"resp722618_2127840\">\n                    <span class=\"under_an\">C</span>. 1,20                </label>\n            ","id":"resp722618_2127840","value":"2127840"},{"content":"\n                <label for=\"resp722618_2127842\">\n                    <span class=\"under_an\">D</span>. 1,50                </label>\n            ","id":"resp722618_2127842","value":"2127842"}]},{"content":"\n    Tiến hành điện phân với điện cực trơ và màng ngăn xốp một dung dịch chứa m gam hỗn hợp CuSO4 và NaCl cho đến khi nước bắt đầu bị điện phân ở cả hai điện cực thì dừng lại. Ở anot thu được 0,896 lít khí (đkc). Dung dịch sau khi điện phân có thể hòa tan tối đa 3,2 gam CuO. Giá trị của m là","info":"\n\t3.\n      ","answers":[{"content":"\n                <label for=\"resp722620_2127924\">\n                    <span class=\"under_an\">A</span>. 11,94                </label>\n            ","id":"resp722620_2127924","value":"2127924"},{"content":"\n                <label for=\"resp722620_2127926\">\n                    <span class=\"under_an\">B</span>. 9,60                </label>\n            ","id":"resp722620_2127926","value":"2127926"},{"content":"\n                <label for=\"resp722620_2127928\">\n                    <span class=\"under_an\">C</span>. 5,97                </label>\n            ","id":"resp722620_2127928","value":"2127928"},{"content":"\n                <label for=\"resp722620_2127930\">\n                    <span class=\"under_an\">D</span>. 6,40                </label>\n            ","id":"resp722620_2127930","value":"2127930"}]},{"content":"\n    Cho 7,68 gam hỗn hợp Fe2O3 và Cu tác dụng với HCl dư, sau phản ứng còn lại 3,2 gam Cu. Khối lượng của Fe2O3 ban đầu là","info":"\n\t4.\n      ","answers":[{"content":"\n                <label for=\"resp722622_2127932\">\n                    <span class=\"under_an\">A</span>. 2,3 gam                </label>\n            ","id":"resp722622_2127932","value":"2127932"},{"content":"\n                <label for=\"resp722622_2127934\">\n                    <span class=\"under_an\">B</span>. 3,2 gam                </label>\n            ","id":"resp722622_2127934","value":"2127934"},{"content":"\n                <label for=\"resp722622_2127936\">\n                    <span class=\"under_an\">C</span>. 4,48 gam                </label>\n            ","id":"resp722622_2127936","value":"2127936"},{"content":"\n                <label for=\"resp722622_2127938\">\n                    <span class=\"under_an\">D</span>. 4,42 gam                </label>\n            ","id":"resp722622_2127938","value":"2127938"}]},{"content":"\n    Cracking khí butan một thời gian thì thu được hỗn hợp khí X gồm CH4, C3H6, C2H6, C2H4 và C4H10 dư. Cho toàn bộ hỗn hợp X đi qua dung dịch nước Br2 dư thì khối lượng bình brom tăng lên 0,91 gam và có 4 gam Br2 phản ứng, đồng thời có hỗn hợp khí Y thoát ra khỏi bình Br2 (thể tích của Y bằng 54,545% thể tích của X). Để đốt cháy hoàn toàn hỗn hợp Y cần vừa đủ V lít O2 (ở đktc). Giá trị của V là","info":"\n\t5.\n      ","answers":[{"content":"\n                <label for=\"resp722624_2127988\">\n                    <span class=\"under_an\">A</span>. 2,184                </label>\n            ","id":"resp722624_2127988","value":"2127988"},{"content":"\n                <label for=\"resp722624_2127990\">\n                    <span class=\"under_an\">B</span>. 4,368                </label>\n            ","id":"resp722624_2127990","value":"2127990"},{"content":"\n                <label for=\"resp722624_2127992\">\n                    <span class=\"under_an\">C</span>. 2,128                </label>\n            ","id":"resp722624_2127992","value":"2127992"},{"content":"\n                <label for=\"resp722624_2127994\">\n                    <span class=\"under_an\">D</span>. 1,736                </label>\n            ","id":"resp722624_2127994","value":"2127994"}]},{"content":"\n    Khi ủ than tổ ong có một khí rất độc, không màu, không mùi được tạo ra, đó là khí?","info":"\n\t6.\n      ","answers":[{"content":"\n                <label for=\"resp722626_2127964\">\n                    <span class=\"under_an\">A</span>. CO<sub>2</sub>                </label>\n            ","id":"resp722626_2127964","value":"2127964"},{"content":"\n                <label for=\"resp722626_2127966\">\n                    <span class=\"under_an\">B</span>. SO<sub>2 </sub>                </label>\n            ","id":"resp722626_2127966","value":"2127966"},{"content":"\n                <label for=\"resp722626_2127968\">\n                    <span class=\"under_an\">C</span>. CO                </label>\n            ","id":"resp722626_2127968","value":"2127968"},{"content":"\n                <label for=\"resp722626_2127970\">\n                    <span class=\"under_an\">D</span>. H<sub>2</sub>                </label>\n            ","id":"resp722626_2127970","value":"2127970"}]},{"content":"\n    Dung dịch chất nào sau đây không làm đổi màu quỳ tím thành đỏ?","info":"\n\t7.\n      ","answers":[{"content":"\n                <label for=\"resp722628_2127884\">\n                    <span class=\"under_an\">A</span>. CH<sub>3</sub>COOH                </label>\n            ","id":"resp722628_2127884","value":"2127884"},{"content":"\n                <label for=\"resp722628_2127886\">\n                    <span class=\"under_an\">B</span>. HOCH<sub>2</sub>COOH                </label>\n            ","id":"resp722628_2127886","value":"2127886"},{"content":"\n                <label for=\"resp722628_2127888\">\n                    <span class=\"under_an\">C</span>. HOOCC<sub>3</sub>H<sub>5</sub>(NH<sub>2</sub>)COOH                </label>\n            ","id":"resp722628_2127888","value":"2127888"},{"content":"\n                <label for=\"resp722628_2127890\">\n                    <span class=\"under_an\">D</span>. H<sub>2</sub>NCH<sub>2</sub>COOH                </label>\n            ","id":"resp722628_2127890","value":"2127890"}]},{"content":"\n    Este nào sau đây có phản ứng tráng bạc?","info":"\n\t8.\n      ","answers":[{"content":"\n                <label for=\"resp722630_2127860\">\n                    <span class=\"under_an\">A</span>. CH<sub>3</sub>COOCH<sub>2</sub>CH<sub>3</sub>                </label>\n            ","id":"resp722630_2127860","value":"2127860"},{"content":"\n                <label for=\"resp722630_2127862\">\n                    <span class=\"under_an\">B</span>. CH<sub>2</sub>=CHCOOCH<sub>3</sub>.                </label>\n            ","id":"resp722630_2127862","value":"2127862"},{"content":"\n                <label for=\"resp722630_2127864\">\n                    <span class=\"under_an\">C</span>. HCOOCH<sub>3</sub>                </label>\n            ","id":"resp722630_2127864","value":"2127864"},{"content":"\n                <label for=\"resp722630_2127866\">\n                    <span class=\"under_an\">D</span>. CH<sub>3</sub>COOCH<sub>3</sub>                </label>\n            ","id":"resp722630_2127866","value":"2127866"}]},{"content":"\n    Hợp chất X có chứa vòng benzen và có công thức phân tử là C7H6Cl2. Thủy phân chất X trong NaOH đặc, ở nhiệt độ cao, áp suất cao thu được chất Y có công thức C7H7O2Na. Số công thức cấu tạo phù hợp của X là","info":"\n\t9.\n      ","answers":[{"content":"\n                <label for=\"resp722632_2127908\">\n                    <span class=\"under_an\">A</span>. 6                </label>\n            ","id":"resp722632_2127908","value":"2127908"},{"content":"\n                <label for=\"resp722632_2127910\">\n                    <span class=\"under_an\">B</span>. 4                </label>\n            ","id":"resp722632_2127910","value":"2127910"},{"content":"\n                <label for=\"resp722632_2127912\">\n                    <span class=\"under_an\">C</span>. 3                </label>\n            ","id":"resp722632_2127912","value":"2127912"},{"content":"\n                <label for=\"resp722632_2127914\">\n                    <span class=\"under_an\">D</span>. 5                </label>\n            ","id":"resp722632_2127914","value":"2127914"}]},{"content":"\n    Cho m gam hỗn hợp X gồm CuO, Fe2O3, FeO tác dụng vừa đủ với 100ml dung dịch chứa H2SO4 1M và HCl 1M. Thể tích (ở đktc) hỗn hợp khí CO và H2 tối thiểu cần dùng để khử hoàn toàn m gam hỗn hợp X là","info":"\n\t10.\n      ","answers":[{"content":"\n                <label for=\"resp722634_2127916\">\n                    <span class=\"under_an\">A</span>. 3,36 lít                </label>\n            ","id":"resp722634_2127916","value":"2127916"},{"content":"\n                <label for=\"resp722634_2127918\">\n                    <span class=\"under_an\">B</span>. 6.72 lit                </label>\n            ","id":"resp722634_2127918","value":"2127918"},{"content":"\n                <label for=\"resp722634_2127920\">\n                    <span class=\"under_an\">C</span>. 1,12 lit                </label>\n            ","id":"resp722634_2127920","value":"2127920"},{"content":"\n                <label for=\"resp722634_2127922\">\n                    <span class=\"under_an\">D</span>. 4,48 lit                </label>\n            ","id":"resp722634_2127922","value":"2127922"}]},{"content":"\n    Cho các phát biểu sau: (1) Glucozơ không tham gia phản ứng công hiđro ( xúc tác Ni, đun nóng). (2) Metyl amin làm quỳ tím ẩm đổi sang màu xanh. (3) Đa số các polime không tan trong các dung môi thông thường. (4) Muối natri hoặc kali của axit béo được dùng để sản xuất xà phòng. Các phát biểu đúng là","info":"\n\t11.\n      ","answers":[{"content":"\n                <label for=\"resp722636_2127900\">\n                    <span class=\"under_an\">A</span>. (1), (2), (3).                </label>\n            ","id":"resp722636_2127900","value":"2127900"},{"content":"\n                <label for=\"resp722636_2127902\">\n                    <span class=\"under_an\">B</span>. (1), (2), (4).                </label>\n            ","id":"resp722636_2127902","value":"2127902"},{"content":"\n                <label for=\"resp722636_2127904\">\n                    <span class=\"under_an\">C</span>. (1), (3), (4).                </label>\n            ","id":"resp722636_2127904","value":"2127904"},{"content":"\n                <label for=\"resp722636_2127906\">\n                    <span class=\"under_an\">D</span>. (2), (3), (4).                </label>\n            ","id":"resp722636_2127906","value":"2127906"}]},{"content":"\n    Cho dãy các polime gồm: tơ tằm, tơ capron, nilon – 6,6, tơ nitron, poli(metyl metacrylat), poli(vinyl clorua), cao su buna, tơ axetat, poli(etylen terephtalat). Số polime được tổng hợp từ phản ứng trùng hợp là:","info":"\n\t12.\n      ","answers":[{"content":"\n                <label for=\"resp722638_2127948\">\n                    <span class=\"under_an\">A</span>. 6                </label>\n            ","id":"resp722638_2127948","value":"2127948"},{"content":"\n                <label for=\"resp722638_2127950\">\n                    <span class=\"under_an\">B</span>. 4                </label>\n            ","id":"resp722638_2127950","value":"2127950"},{"content":"\n                <label for=\"resp722638_2127952\">\n                    <span class=\"under_an\">C</span>. 5                </label>\n            ","id":"resp722638_2127952","value":"2127952"},{"content":"\n                <label for=\"resp722638_2127954\">\n                    <span class=\"under_an\">D</span>. 7                </label>\n            ","id":"resp722638_2127954","value":"2127954"}]},{"content":"\n    Kim loại nào sau đây có tính khử yếu nhất?","info":"\n\t13.\n      ","answers":[{"content":"\n                <label for=\"resp722640_2127852\">\n                    <span class=\"under_an\">A</span>. Cr                </label>\n            ","id":"resp722640_2127852","value":"2127852"},{"content":"\n                <label for=\"resp722640_2127854\">\n                    <span class=\"under_an\">B</span>. Al                </label>\n            ","id":"resp722640_2127854","value":"2127854"},{"content":"\n                <label for=\"resp722640_2127856\">\n                    <span class=\"under_an\">C</span>. Fe                </label>\n            ","id":"resp722640_2127856","value":"2127856"},{"content":"\n                <label for=\"resp722640_2127858\">\n                    <span class=\"under_an\">D</span>. Cu                </label>\n            ","id":"resp722640_2127858","value":"2127858"}]},{"content":"\n    Hòa tan hoàn toàn 42,90 gam Zn trong lượng vừa đủ V mol dung dịch HNO3 10% (d = 1,26 g/ml), sau phản ứng thu được dung dịch A chứa 129,54 gam hai muối tan và 4,032 lít (ở đktc) hỗn hợp 2 khí NO và N2O. Giá trị của V là","info":"\n\t14.\n      ","answers":[{"content":"\n                <label for=\"resp722642_2127876\">\n                    <span class=\"under_an\">A</span>. 840                </label>\n            ","id":"resp722642_2127876","value":"2127876"},{"content":"\n                <label for=\"resp722642_2127878\">\n                    <span class=\"under_an\">B</span>. 857                </label>\n            ","id":"resp722642_2127878","value":"2127878"},{"content":"\n                <label for=\"resp722642_2127880\">\n                    <span class=\"under_an\">C</span>. 540                </label>\n            ","id":"resp722642_2127880","value":"2127880"},{"content":"\n                <label for=\"resp722642_2127882\">\n                    <span class=\"under_an\">D</span>. 1336                </label>\n            ","id":"resp722642_2127882","value":"2127882"}]},{"content":"\n    Thủy phân este X có CTPT C4H6O2. Khi X tác dụng với dung dịch NaOH thu được hỗn hợp 2 chất hữu cơ Y và Z trong đó Z có tỉ khối hơi so với H2 là 16. Tên của X là","info":"\n\t15.\n      ","answers":[{"content":"\n                <label for=\"resp722644_2127940\">\n                    <span class=\"under_an\">A</span>. Metyl propionat                </label>\n            ","id":"resp722644_2127940","value":"2127940"},{"content":"\n                <label for=\"resp722644_2127942\">\n                    <span class=\"under_an\">B</span>. Etyl axetat                </label>\n            ","id":"resp722644_2127942","value":"2127942"},{"content":"\n                <label for=\"resp722644_2127944\">\n                    <span class=\"under_an\">C</span>. Metyl axetat                </label>\n            ","id":"resp722644_2127944","value":"2127944"},{"content":"\n                <label for=\"resp722644_2127946\">\n                    <span class=\"under_an\">D</span>. Metyl acrylat                </label>\n            ","id":"resp722644_2127946","value":"2127946"}]},{"content":"\n    Phenol không có khả năng phản ứng với chất nào sau đây?","info":"\n\t16.\n      ","answers":[{"content":"\n                <label for=\"resp722646_2127892\">\n                    <span class=\"under_an\">A</span>. Dung dịch NaCl.                </label>\n            ","id":"resp722646_2127892","value":"2127892"},{"content":"\n                <label for=\"resp722646_2127894\">\n                    <span class=\"under_an\">B</span>. Nước Br<sub>2</sub>                </label>\n            ","id":"resp722646_2127894","value":"2127894"},{"content":"\n                <label for=\"resp722646_2127896\">\n                    <span class=\"under_an\">C</span>. Dung dịch NaOH                </label>\n            ","id":"resp722646_2127896","value":"2127896"},{"content":"\n                <label for=\"resp722646_2127898\">\n                    <span class=\"under_an\">D</span>. Kim loại Na                </label>\n            ","id":"resp722646_2127898","value":"2127898"}]},{"content":"\n    Dãy gồm các ion cùng tồn tại trong một dung dịch là","info":"\n\t17.\n      ","answers":[{"content":"\n                <label for=\"resp722648_2127972\">\n                    <span class=\"under_an\">A</span>. K<sup>+</sup>, Ba<sup>2+</sup>, OH<sup>-</sup>, Cl<sup>-</sup>                </label>\n            ","id":"resp722648_2127972","value":"2127972"},{"content":"\n                <label for=\"resp722648_2127974\">\n                    <span class=\"under_an\">B</span>. Al<sup>3+</sup>, P0<sub>4</sub><sup>3-</sup>, Cl<sup>-</sup>, Ba<sup>2+ </sup>                </label>\n            ","id":"resp722648_2127974","value":"2127974"},{"content":"\n                <label for=\"resp722648_2127976\">\n                    <span class=\"under_an\">C</span>. Na<sup>+</sup>, K<sup>+</sup>, OH<sup>-</sup>, HCO<sub>3</sub><sup>- </sup>                </label>\n            ","id":"resp722648_2127976","value":"2127976"},{"content":"\n                <label for=\"resp722648_2127978\">\n                    <span class=\"under_an\">D</span>. Ca<sup>2+</sup>, Cl<sup>-</sup>, Na<sup>+</sup>, CO<sub>3</sub><sup>2- </sup>                </label>\n            ","id":"resp722648_2127978","value":"2127978"}]},{"content":"\n    Chất nào sau đây không phải là chất điện ly?","info":"\n\t18.\n      ","answers":[{"content":"\n                <label for=\"resp722650_2127868\">\n                    <span class=\"under_an\">A</span>. NaCl                </label>\n            ","id":"resp722650_2127868","value":"2127868"},{"content":"\n                <label for=\"resp722650_2127870\">\n                    <span class=\"under_an\">B</span>. C<sub>2</sub>H<sub>5</sub>OH                </label>\n            ","id":"resp722650_2127870","value":"2127870"},{"content":"\n                <label for=\"resp722650_2127872\">\n                    <span class=\"under_an\">C</span>. NaOH                </label>\n            ","id":"resp722650_2127872","value":"2127872"},{"content":"\n                <label for=\"resp722650_2127874\">\n                    <span class=\"under_an\">D</span>. H<sub>2</sub>SO<sub>4</sub>                </label>\n            ","id":"resp722650_2127874","value":"2127874"}]},{"content":"\n    X, Y (MX< MY) là hai peptit mạch hở, hơn kém nhau một liên kết peptit. Đun nóng 36,58 gam hỗn hợp E chứa X, Y và este Z (C5H11O2N) với dung dịch NaOH vừa đủ, chưng cất dung dịch sau phản ứng, thu được 0,05 mol ancol etylic và hỗn hợp chứa 2 muối của 2 α-aminoaxit thuộc cùng dãy đồng đẳng. Đốt cháy toàn bộ muối cần dùng 1,59 mol O2, thu được CO2, H2O, N2 và 26,5 gam Na2CO3. Phần trăm khối lượng của X trong hỗn hợp E là.","info":"\n\t19.\n      ","answers":[{"content":"\n                <label for=\"resp722652_2127844\">\n                    <span class=\"under_an\">A</span>. 45,2%                </label>\n            ","id":"resp722652_2127844","value":"2127844"},{"content":"\n                <label for=\"resp722652_2127846\">\n                    <span class=\"under_an\">B</span>. 29,8%                </label>\n            ","id":"resp722652_2127846","value":"2127846"},{"content":"\n                <label for=\"resp722652_2127848\">\n                    <span class=\"under_an\">C</span>. 34,1%                </label>\n            ","id":"resp722652_2127848","value":"2127848"},{"content":"\n                <label for=\"resp722652_2127850\">\n                    <span class=\"under_an\">D</span>. 27,1%                </label>\n            ","id":"resp722652_2127850","value":"2127850"}]},{"content":"\n    Một dung dịch X chứa 0,01 mol Ba2+, 0,01 mol NO3–, a mol OH–, b mol Na+. Để trung hòa lượng dung dịch X này cần dùng 400 ml dung dịch HCl có pH = 1. Khối lượng chất rắn thu được sau khi cô cạn dung dịch X nói trên là","info":"\n\t20.\n      ","answers":[{"content":"\n                <label for=\"resp722654_2127956\">\n                    <span class=\"under_an\">A</span>. 1,68 gam                </label>\n            ","id":"resp722654_2127956","value":"2127956"},{"content":"\n                <label for=\"resp722654_2127958\">\n                    <span class=\"under_an\">B</span>. 2,56 gam                </label>\n            ","id":"resp722654_2127958","value":"2127958"},{"content":"\n                <label for=\"resp722654_2127960\">\n                    <span class=\"under_an\">C</span>. 3,36 gam                </label>\n            ","id":"resp722654_2127960","value":"2127960"},{"content":"\n                <label for=\"resp722654_2127962\">\n                    <span class=\"under_an\">D</span>. 3,42 gam                </label>\n            ","id":"resp722654_2127962","value":"2127962"}]}]},{"tag":{"title":"Kiểm tra môn Toán - HOCMAI"},"title":"Bài tập tự luyện","subtitle":"ĐỀ DÀNH CHO HỌC SINH LỚP 12","questions":[{"content":"\n    Cho elip \\[\\left( E \\right): \\frac{{{x}^{\\text{2}}}}{\\text{16}}\\text{+}\\frac{{{y}^{\\text{2}}}}{\\text{7}}=1\\]. Khoảng cách giữa hai đường chuẩn của elip là","info":"\n\t1.\n      ","answers":[{"content":"\n                <label for=\"resp722812_2129266\">\n                    <span class=\"under_an\">A</span>. \\[\\pm \\frac{16}{3}\\].                </label>\n            ","id":"resp722812_2129266","value":"2129266"},{"content":"\n                <label for=\"resp722812_2129262\">\n                    <span class=\"under_an\">B</span>. \\[\\frac{16}{3}\\].                </label>\n            ","id":"resp722812_2129262","value":"2129262"},{"content":"\n                <label for=\"resp722812_2129264\">\n                    <span class=\"under_an\">C</span>. \\[16\\].                </label>\n            ","id":"resp722812_2129264","value":"2129264"},{"content":"\n                <label for=\"resp722812_2129260\">\n                    <span class=\"under_an\">D</span>. \\[\\frac{32}{3}\\].                </label>\n            ","id":"resp722812_2129260","value":"2129260"}]},{"content":"\n    Trong mặt phẳng với hệ tọa độ  $$ Oxy, $$  cho tam giác  $$ ABC $$  cân, cạnh đáy  $$ BC $$  có phương trình.  $$ x+y+1=0, $$  phương trình đường cao kẻ từ  $$ B $$  là.  $$ x-2y-2=0.  $$  Tọa độ điểm  $$ B $$  là","info":"\n\t2.\n      ","answers":[{"content":"\n                <label for=\"resp722814_2129274\">\n                    <span class=\"under_an\">A</span>. $$ B\\left( 1;2 \\right) $$                </label>\n            ","id":"resp722814_2129274","value":"2129274"},{"content":"\n                <label for=\"resp722814_2129268\">\n                    <span class=\"under_an\">B</span>. $$ B\\left( 0;-1 \\right) $$                </label>\n            ","id":"resp722814_2129268","value":"2129268"},{"content":"\n                <label for=\"resp722814_2129272\">\n                    <span class=\"under_an\">C</span>. $$ B\\left( 1;-1 \\right) $$                </label>\n            ","id":"resp722814_2129272","value":"2129272"},{"content":"\n                <label for=\"resp722814_2129270\">\n                    <span class=\"under_an\">D</span>. $$ B\\left( 0;1 \\right) $$                </label>\n            ","id":"resp722814_2129270","value":"2129270"}]},{"content":"\n    Tìm giá trị nhỏ nhất của hàm số  $$ f\\left( x \\right)=x+\\frac{2}{x-1} $$  với  $$ x>1 $$","info":"\n\t3.\n      ","answers":[{"content":"\n                <label for=\"resp722798_2129204\">\n                    <span class=\"under_an\">A</span>. $$ 2\\sqrt{2}-1 $$                </label>\n            ","id":"resp722798_2129204","value":"2129204"},{"content":"\n                <label for=\"resp722798_2129208\">\n                    <span class=\"under_an\">B</span>. $$ 2\\sqrt{2} $$                </label>\n            ","id":"resp722798_2129208","value":"2129208"},{"content":"\n                <label for=\"resp722798_2129210\">\n                    <span class=\"under_an\">C</span>. $$ -2\\sqrt{2} $$                </label>\n            ","id":"resp722798_2129210","value":"2129210"},{"content":"\n                <label for=\"resp722798_2129206\">\n                    <span class=\"under_an\">D</span>. $$ 2\\sqrt{2}+1 $$                </label>\n            ","id":"resp722798_2129206","value":"2129206"}]},{"content":"\n    Một xí nghiệp sản xuất hai loại sản phẩm kí hiệu I và II. Một tấn sản phẩm I lãi 2 triệu đồng, một tấn sản phẩm II lãi 1,6 triệu đồng. Muốn sản xuất 1 tấn sản phẩm I phải dùng máy  $$ {{M}_{1}} $$  trong 3 giờ và máy  $$ {{M}_{2}} $$  trong 1 giờ. Muốn sản xuất 1 tấn sản phẩm II phải dùng máy  $$ {{M}_{1}} $$  trong 1 giờ và máy  $$ {{M}_{2}} $$  trong 1 giờ. Biết rằng một máy không thể dùng để sản xuất đồng thời hai loại sản phẩm; máy  $$ {{M}_{1}} $$  làm việc không quá 6 giờ trong một ngày, máy  $$ {{M}_{2}} $$  một ngày chỉ làm việc không quá 4 giờ. Tổng số sản phẩm II mà xí nghiệp nên sản xuất trong 1 tuần để số tiền lãi lớn nhất là.","info":"\n\t4.\n      ","answers":[{"content":"\n                <label for=\"resp722800_2129212\">\n                    <span class=\"under_an\">A</span>. 3                </label>\n            ","id":"resp722800_2129212","value":"2129212"},{"content":"\n                <label for=\"resp722800_2129216\">\n                    <span class=\"under_an\">B</span>. 21                </label>\n            ","id":"resp722800_2129216","value":"2129216"},{"content":"\n                <label for=\"resp722800_2129218\">\n                    <span class=\"under_an\">C</span>. 28                </label>\n            ","id":"resp722800_2129218","value":"2129218"},{"content":"\n                <label for=\"resp722800_2129214\">\n                    <span class=\"under_an\">D</span>. 4                </label>\n            ","id":"resp722800_2129214","value":"2129214"}]},{"content":"\n    Trong năm phép biến hình. Tịnh tiến, đối xứng tâm, đối xứng trục, phép quay và phép vị tự. Có bao nhiêu phép biến hình luôn biến một đường thẳng thành đường thẳng song song hoặc trùng với nó?","info":"\n\t5.\n      ","answers":[{"content":"\n                <label for=\"resp722786_2129158\">\n                    <span class=\"under_an\">A</span>. \\[2\\].                </label>\n            ","id":"resp722786_2129158","value":"2129158"},{"content":"\n                <label for=\"resp722786_2129160\">\n                    <span class=\"under_an\">B</span>. \\[3\\].                </label>\n            ","id":"resp722786_2129160","value":"2129160"},{"content":"\n                <label for=\"resp722786_2129156\">\n                    <span class=\"under_an\">C</span>. \\[1\\].                </label>\n            ","id":"resp722786_2129156","value":"2129156"},{"content":"\n                <label for=\"resp722786_2129162\">\n                    <span class=\"under_an\">D</span>. \\[4\\].                </label>\n            ","id":"resp722786_2129162","value":"2129162"}]},{"content":"\n    Có bao nhiêu giá trị nguyên của \\[a\\] để phương trình \\[{{\\cos }^{3}}2x-{{\\cos }^{2}}2x-a{{\\sin }^{2}}x=0\\] có nghiệm thuộc khoảng \\[\\left( 0;\\frac{\\pi }{6} \\right)\\].","info":"\n\t6.\n      ","answers":[{"content":"\n                <label for=\"resp722782_2129142\">\n                    <span class=\"under_an\">A</span>. \\[1\\].                </label>\n            ","id":"resp722782_2129142","value":"2129142"},{"content":"\n                <label for=\"resp722782_2129146\">\n                    <span class=\"under_an\">B</span>. \\[3\\].                </label>\n            ","id":"resp722782_2129146","value":"2129146"},{"content":"\n                <label for=\"resp722782_2129144\">\n                    <span class=\"under_an\">C</span>. \\[2\\].                </label>\n            ","id":"resp722782_2129144","value":"2129144"},{"content":"\n                <label for=\"resp722782_2129140\">\n                    <span class=\"under_an\">D</span>. \\[0\\].                </label>\n            ","id":"resp722782_2129140","value":"2129140"}]},{"content":"\n    Gọi \\[a\\] là hệ số không chứa \\[x\\] trong khai triển khai triển nhị thức Niu – tơn \\[{{\\left( {{x}^{2}}-\\frac{2}{\\sqrt{x}} \\right)}^{n}}=C_{n}^{0}{{\\left( {{x}^{2}} \\right)}^{n}}+C_{n}^{1}{{\\left( {{x}^{2}} \\right)}^{n-1}}\\left( \\frac{-2}{\\sqrt{x}} \\right)+... +C_{n}^{n-1}\\left( {{x}^{2}} \\right){{\\left( \\frac{-2}{\\sqrt{x}} \\right)}^{n-1}}+C_{n}^{n}{{\\left( \\frac{-2}{\\sqrt{x}} \\right)}^{n}}\\] (\\[n\\] là số nguyên dương(.\n Biết rằng trong khai triển trên tổng hệ số của ba số hạng đầu bằng \\[161\\]. Tìm \\[a\\].","info":"\n\t7.\n      ","answers":[{"content":"\n                <label for=\"resp722780_2129138\">\n                    <span class=\"under_an\">A</span>. \\[a=10125\\].                </label>\n            ","id":"resp722780_2129138","value":"2129138"},{"content":"\n                <label for=\"resp722780_2129134\">\n                    <span class=\"under_an\">B</span>. \\[a=11250\\].                </label>\n            ","id":"resp722780_2129134","value":"2129134"},{"content":"\n                <label for=\"resp722780_2129136\">\n                    <span class=\"under_an\">C</span>. \\[a=12150\\].                </label>\n            ","id":"resp722780_2129136","value":"2129136"},{"content":"\n                <label for=\"resp722780_2129132\">\n                    <span class=\"under_an\">D</span>. \\[a=11520\\].                </label>\n            ","id":"resp722780_2129132","value":"2129132"}]},{"content":"\n    Tập nghiệm của bất phương trình  $$ \\left| \\left| x \\right|-1 \\right|<1-x $$  là  $$ \\left( -\\infty ;a \\right) $$ . Khẳng định nào sau đây là đúng","info":"\n\t8.\n      ","answers":[{"content":"\n                <label for=\"resp722802_2129222\">\n                    <span class=\"under_an\">A</span>. $$ a $$  là số vô tỉ                </label>\n            ","id":"resp722802_2129222","value":"2129222"},{"content":"\n                <label for=\"resp722802_2129224\">\n                    <span class=\"under_an\">B</span>. $$ a $$  là phân số hữu tỉ                </label>\n            ","id":"resp722802_2129224","value":"2129224"},{"content":"\n                <label for=\"resp722802_2129226\">\n                    <span class=\"under_an\">C</span>. $$ a $$  là số nguyên âm                </label>\n            ","id":"resp722802_2129226","value":"2129226"},{"content":"\n                <label for=\"resp722802_2129220\">\n                    <span class=\"under_an\">D</span>. $$ a=0 $$                </label>\n            ","id":"resp722802_2129220","value":"2129220"}]},{"content":"\n    Có \\[60\\] tấm thẻ đánh số từ \\[1\\] đến \\[60\\]. Rút ngẫu nhiên \\[3\\] thẻ. Tính xác suất để tổng các số ghi trên \\[3\\] thẻ chia hết cho \\[3\\].","info":"\n\t9.\n      ","answers":[{"content":"\n                <label for=\"resp722788_2129170\">\n                    <span class=\"under_an\">A</span>. \\[\\frac{571}{1711}\\].                </label>\n            ","id":"resp722788_2129170","value":"2129170"},{"content":"\n                <label for=\"resp722788_2129166\">\n                    <span class=\"under_an\">B</span>. \\[\\frac{1}{12}\\].                </label>\n            ","id":"resp722788_2129166","value":"2129166"},{"content":"\n                <label for=\"resp722788_2129164\">\n                    <span class=\"under_an\">C</span>. \\[\\frac{171}{1711}\\].                </label>\n            ","id":"resp722788_2129164","value":"2129164"},{"content":"\n                <label for=\"resp722788_2129168\">\n                    <span class=\"under_an\">D</span>. \\[\\frac{9}{89}\\].                </label>\n            ","id":"resp722788_2129168","value":"2129168"}]},{"content":"\n    Điều kiện biến đổi tương đương của bất đẳng thức  $$ {{a}^{2}}>{{b}^{2}}\\Leftrightarrow a>b $$  là.","info":"\n\t10.\n      ","answers":[{"content":"\n                <label for=\"resp722796_2129200\">\n                    <span class=\"under_an\">A</span>. $$ a&gt;0,b&lt;0 $$                </label>\n            ","id":"resp722796_2129200","value":"2129200"},{"content":"\n                <label for=\"resp722796_2129196\">\n                    <span class=\"under_an\">B</span>. $$ a,b&gt;0 $$                </label>\n            ","id":"resp722796_2129196","value":"2129196"},{"content":"\n                <label for=\"resp722796_2129202\">\n                    <span class=\"under_an\">C</span>. $$ a&lt;0,b&gt;0 $$                </label>\n            ","id":"resp722796_2129202","value":"2129202"},{"content":"\n                <label for=\"resp722796_2129198\">\n                    <span class=\"under_an\">D</span>. $$ a,b&lt;0 $$                </label>\n            ","id":"resp722796_2129198","value":"2129198"}]},{"content":"\n    Biết \\[\\underset{x\\to 1}{\\mathop{\\lim }}\\,\\frac{\\sqrt{x}-1}{{{x}^{2}}+ax+2}=b\\], với \\[a,b\\] là các số thực khác \\[0\\]. Tính giá trị của biểu thức \\[T=a+b\\].","info":"\n\t11.\n      ","answers":[{"content":"\n                <label for=\"resp722792_2129180\">\n                    <span class=\"under_an\">A</span>. \\[\\frac{5}{2}\\].                </label>\n            ","id":"resp722792_2129180","value":"2129180"},{"content":"\n                <label for=\"resp722792_2129184\">\n                    <span class=\"under_an\">B</span>. \\[\\frac{3}{2}\\].                </label>\n            ","id":"resp722792_2129184","value":"2129184"},{"content":"\n                <label for=\"resp722792_2129186\">\n                    <span class=\"under_an\">C</span>. \\[-\\frac{7}{2}\\].                </label>\n            ","id":"resp722792_2129186","value":"2129186"},{"content":"\n                <label for=\"resp722792_2129182\">\n                    <span class=\"under_an\">D</span>. \\[-\\frac{5}{2}\\].                </label>\n            ","id":"resp722792_2129182","value":"2129182"}]},{"content":"\n    Đường thẳng  $$ \\left( \\Delta\n \\right): 5x+3y=15 $$  tạo với các trục tọa độ một tam giác có diện tích bằng bao nhiêu?","info":"\n\t12.\n      ","answers":[{"content":"\n                <label for=\"resp722808_2129246\">\n                    <span class=\"under_an\">A</span>. $$ 15 $$ .                </label>\n            ","id":"resp722808_2129246","value":"2129246"},{"content":"\n                <label for=\"resp722808_2129250\">\n                    <span class=\"under_an\">B</span>. $$ 5 $$ .                </label>\n            ","id":"resp722808_2129250","value":"2129250"},{"content":"\n                <label for=\"resp722808_2129244\">\n                    <span class=\"under_an\">C</span>. $$ 3 $$ .                </label>\n            ","id":"resp722808_2129244","value":"2129244"},{"content":"\n                <label for=\"resp722808_2129248\">\n                    <span class=\"under_an\">D</span>. $$ \\frac{15}{2} $$ .                </label>\n            ","id":"resp722808_2129248","value":"2129248"}]},{"content":"\n    Cho phương trình chính tắc của Prabol  $$ \\left( P \\right): {{x}^{2}}=2py $$ , khi đó phương trình đường chuẩn của  $$ \\left( P \\right) $$  là.","info":"\n\t13.\n      ","answers":[{"content":"\n                <label for=\"resp722810_2129258\">\n                    <span class=\"under_an\">A</span>. $$ y=-\\frac{p}{2} $$                </label>\n            ","id":"resp722810_2129258","value":"2129258"},{"content":"\n                <label for=\"resp722810_2129252\">\n                    <span class=\"under_an\">B</span>. $$ x=\\frac{p}{2} $$                </label>\n            ","id":"resp722810_2129252","value":"2129252"},{"content":"\n                <label for=\"resp722810_2129254\">\n                    <span class=\"under_an\">C</span>. $$ x=-\\frac{p}{2} $$                </label>\n            ","id":"resp722810_2129254","value":"2129254"},{"content":"\n                <label for=\"resp722810_2129256\">\n                    <span class=\"under_an\">D</span>. $$ y=\\frac{p}{2} $$                </label>\n            ","id":"resp722810_2129256","value":"2129256"}]},{"content":"\n    Cho cấp số cộng \\[\\left( {{u}_{n}} \\right)\\] với số hạng đầu \\[{{u}_{1}}=2\\] và số hạng thứ năm \\[{{u}_{5}}=14\\]. Tổng của 10 số hạng đầu của cấp số cộng \\[\\left( {{u}_{n}} \\right)\\] là","info":"\n\t14.\n      ","answers":[{"content":"\n                <label for=\"resp722778_2129124\">\n                    <span class=\"under_an\">A</span>. \\[232\\].                </label>\n            ","id":"resp722778_2129124","value":"2129124"},{"content":"\n                <label for=\"resp722778_2129130\">\n                    <span class=\"under_an\">B</span>. \\[187\\].                </label>\n            ","id":"resp722778_2129130","value":"2129130"},{"content":"\n                <label for=\"resp722778_2129128\">\n                    <span class=\"under_an\">C</span>. \\[155\\].                </label>\n            ","id":"resp722778_2129128","value":"2129128"},{"content":"\n                <label for=\"resp722778_2129126\">\n                    <span class=\"under_an\">D</span>. \\[126\\].                </label>\n            ","id":"resp722778_2129126","value":"2129126"}]},{"content":"\n    Có 5 đoạn thẳng có độ dài lần lượt là 1cm, 2cm, 3cm, 4cm, 5cm. Lấy ngẫu nhiên ra 3 đoạn thẳng, tính xác suất để 3 đoạn thẳng được chọn ra là độ dài 3 cạnh của 1 tam giác.","info":"\n\t15.\n      ","answers":[{"content":"\n                <label for=\"resp722784_2129152\">\n                    <span class=\"under_an\">A</span>. \\[\\frac{3}{10}\\].                </label>\n            ","id":"resp722784_2129152","value":"2129152"},{"content":"\n                <label for=\"resp722784_2129154\">\n                    <span class=\"under_an\">B</span>. \\[\\frac{1}{10}\\].                </label>\n            ","id":"resp722784_2129154","value":"2129154"},{"content":"\n                <label for=\"resp722784_2129148\">\n                    <span class=\"under_an\">C</span>. \\[\\frac{3}{5}\\].                </label>\n            ","id":"resp722784_2129148","value":"2129148"},{"content":"\n                <label for=\"resp722784_2129150\">\n                    <span class=\"under_an\">D</span>. \\[\\frac{2}{5}\\].                </label>\n            ","id":"resp722784_2129150","value":"2129150"}]},{"content":"\n    Tích các nghiệm nguyên của bất phương trình  $$ \\left( x+1 \\right)\\sqrt{x+2}+\\left( x+6 \\right)\\sqrt{x+7}\\ge {{x}^{2}}+7x+12 $$  là.","info":"\n\t16.\n      ","answers":[{"content":"\n                <label for=\"resp722804_2129232\">\n                    <span class=\"under_an\">A</span>. 0                </label>\n            ","id":"resp722804_2129232","value":"2129232"},{"content":"\n                <label for=\"resp722804_2129228\">\n                    <span class=\"under_an\">B</span>. 2                </label>\n            ","id":"resp722804_2129228","value":"2129228"},{"content":"\n                <label for=\"resp722804_2129234\">\n                    <span class=\"under_an\">C</span>. \\[-1\\]                </label>\n            ","id":"resp722804_2129234","value":"2129234"},{"content":"\n                <label for=\"resp722804_2129230\">\n                    <span class=\"under_an\">D</span>. 3                </label>\n            ","id":"resp722804_2129230","value":"2129230"}]},{"content":"\n    Cho cấp số cộng \\[\\left( {{u}_{n}} \\right)\\] với công sai \\[d=5\\] và \\[{{u}_{4}}=4{{u}_{1}}\\]. Tìm \\[{{u}_{100}}\\].","info":"\n\t17.\n      ","answers":[{"content":"\n                <label for=\"resp722790_2129174\">\n                    <span class=\"under_an\">A</span>. \\[{{u}_{100}}=250\\].                </label>\n            ","id":"resp722790_2129174","value":"2129174"},{"content":"\n                <label for=\"resp722790_2129176\">\n                    <span class=\"under_an\">B</span>. \\[{{u}_{100}}=500\\].                </label>\n            ","id":"resp722790_2129176","value":"2129176"},{"content":"\n                <label for=\"resp722790_2129178\">\n                    <span class=\"under_an\">C</span>. \\[{{u}_{100}}=750\\].                </label>\n            ","id":"resp722790_2129178","value":"2129178"},{"content":"\n                <label for=\"resp722790_2129172\">\n                    <span class=\"under_an\">D</span>. \\[{{u}_{100}}=100\\].                </label>\n            ","id":"resp722790_2129172","value":"2129172"}]},{"content":"\n    Cho tứ diện \\[ABCD\\] có \\[AB=CD=2a\\]. Gọi \\[M,N\\] lần lượt là trung điểm của \\[BC,AD\\] và \\[MN=a\\sqrt{3}\\]. Tính góc tạo bởi hai đường thẳng \\[AB\\] và \\[CD\\].","info":"\n\t18.\n      ","answers":[{"content":"\n                <label for=\"resp722776_2129120\">\n                    <span class=\"under_an\">A</span>. \\[{{60}^{0}}\\].                </label>\n            ","id":"resp722776_2129120","value":"2129120"},{"content":"\n                <label for=\"resp722776_2129116\">\n                    <span class=\"under_an\">B</span>. \\[{{30}^{0}}\\].                </label>\n            ","id":"resp722776_2129116","value":"2129116"},{"content":"\n                <label for=\"resp722776_2129122\">\n                    <span class=\"under_an\">C</span>. \\[{{90}^{0}}\\].                </label>\n            ","id":"resp722776_2129122","value":"2129122"},{"content":"\n                <label for=\"resp722776_2129118\">\n                    <span class=\"under_an\">D</span>. \\[{{45}^{0}}\\].                </label>\n            ","id":"resp722776_2129118","value":"2129118"}]},{"content":"\n    Trong các số từ \\[100\\] đến \\[999\\] có bao nhiêu số mà các chữ số của nó tăng dần hoặc giảm dần?","info":"\n\t19.\n      ","answers":[{"content":"\n                <label for=\"resp722794_2129194\">\n                    <span class=\"under_an\">A</span>. \\[168\\].                </label>\n            ","id":"resp722794_2129194","value":"2129194"},{"content":"\n                <label for=\"resp722794_2129192\">\n                    <span class=\"under_an\">B</span>. \\[240\\].                </label>\n            ","id":"resp722794_2129192","value":"2129192"},{"content":"\n                <label for=\"resp722794_2129188\">\n                    <span class=\"under_an\">C</span>. \\[1224\\].                </label>\n            ","id":"resp722794_2129188","value":"2129188"},{"content":"\n                <label for=\"resp722794_2129190\">\n                    <span class=\"under_an\">D</span>. \\[204\\].                </label>\n            ","id":"resp722794_2129190","value":"2129190"}]},{"content":"\n    Trong các câu khẳng định sau, câu nào là mệnh đề sai?","info":"\n\t20.\n      ","answers":[{"content":"\n                <label for=\"resp722806_2129240\">\n                    <span class=\"under_an\">A</span>. Nếu một phương trình bậc hai có biệt thức ∆ không âm thì nó có nghiệm.                </label>\n            ","id":"resp722806_2129240","value":"2129240"},{"content":"\n                <label for=\"resp722806_2129242\">\n                    <span class=\"under_an\">B</span>. Tổng 3 góc trong của một tam giác bằng \\[{{180}^{0}}\\]                </label>\n            ","id":"resp722806_2129242","value":"2129242"},{"content":"\n                <label for=\"resp722806_2129238\">\n                    <span class=\"under_an\">C</span>. 2 là số nguyên tố.                </label>\n            ","id":"resp722806_2129238","value":"2129238"},{"content":"\n                <label for=\"resp722806_2129236\">\n                    <span class=\"under_an\">D</span>. Nếu tam giác ABC thỏa mãn \\[A{{B}^{2}}+A{{C}^{2}}=B{{C}^{2}}\\] thì tam giác ABC vuông tại A                </label>\n            ","id":"resp722806_2129236","value":"2129236"}]}]},{"tag":{"title":"Kiểm tra môn Toán - HOCMAI"},"title":"Bài tập tự luyện","subtitle":"ĐỀ DÀNH CHO HỌC SINH LỚP 13","questions":[{"content":"\n    Cho hình chóp \\[S. ABC\\] có đáy \\[ABC\\] là tam giác vuông cân tại \\[B\\], \\[AB=BC=a\\sqrt{3}\\]\\[,\\]\\[\\widehat{SAB}=\\widehat{SCB}={{90}^{0}}\\], khoảng cách từ \\[A\\] tới mặt phẳng \\[(SBC)\\] bằng \\[a\\sqrt{2}\\]. Diện tích mặt cầu ngoại tiếp hình chóp \\[S. ABC\\] theo \\[a\\] là","info":"\n\t1.\n      ","answers":[{"content":"\n                <label for=\"resp722848_2129406\">\n                    <span class=\"under_an\">A</span>. \\[3\\pi {{a}^{2}}\\].                </label>\n            ","id":"resp722848_2129406","value":"2129406"},{"content":"\n                <label for=\"resp722848_2129410\">\n                    <span class=\"under_an\">B</span>. \\[12\\pi {{a}^{2}}\\].                </label>\n            ","id":"resp722848_2129410","value":"2129410"},{"content":"\n                <label for=\"resp722848_2129408\">\n                    <span class=\"under_an\">C</span>. \\[16\\pi {{a}^{2}}\\].                </label>\n            ","id":"resp722848_2129408","value":"2129408"},{"content":"\n                <label for=\"resp722848_2129404\">\n                    <span class=\"under_an\">D</span>. \\[2\\pi {{a}^{2}}\\].                </label>\n            ","id":"resp722848_2129404","value":"2129404"}]},{"content":"\n    Cho hàm số \\[f\\left( x \\right)=\\left\\{ \\begin{array}{l}\n \\frac{\\sqrt{x}-1}{x-1}\\text{\n khi }x>1 \\\\\n mx+1\\text{\n khi }x\\le 1 \n \\end{array} \\right. \\]. Tìm tất cả các giá trị của m để \\[f\\left( x \\right)\\] liên tục trên tập  $$ \\mathbb{R} $$ .","info":"\n\t2.\n      ","answers":[{"content":"\n                <label for=\"resp722846_2129396\">\n                    <span class=\"under_an\">A</span>. $$ m=2 $$ .                </label>\n            ","id":"resp722846_2129396","value":"2129396"},{"content":"\n                <label for=\"resp722846_2129398\">\n                    <span class=\"under_an\">B</span>. $$ m=\\frac{1}{2} $$ .                </label>\n            ","id":"resp722846_2129398","value":"2129398"},{"content":"\n                <label for=\"resp722846_2129402\">\n                    <span class=\"under_an\">C</span>. $$ m=-\\frac{1}{2} $$ .                </label>\n            ","id":"resp722846_2129402","value":"2129402"},{"content":"\n                <label for=\"resp722846_2129400\">\n                    <span class=\"under_an\">D</span>. $$ m=-2 $$ .                </label>\n            ","id":"resp722846_2129400","value":"2129400"}]},{"content":"\n    Biết đồ thị hàm số \\[y=x-\\sqrt{{{x}^{2}}-mx+1}\\] có tiệm cận ngang \\[y=1\\]. Khi đó giá trị thực của \\[m\\] thuộc khoảng nào trong các khoảng sau?","info":"\n\t3.\n      ","answers":[{"content":"\n                <label for=\"resp722822_2129306\">\n                    <span class=\"under_an\">A</span>. \\[(3;5)\\].                </label>\n            ","id":"resp722822_2129306","value":"2129306"},{"content":"\n                <label for=\"resp722822_2129304\">\n                    <span class=\"under_an\">B</span>. \\[(2;4)\\].                </label>\n            ","id":"resp722822_2129304","value":"2129304"},{"content":"\n                <label for=\"resp722822_2129300\">\n                    <span class=\"under_an\">C</span>. \\[(0;2)\\].                </label>\n            ","id":"resp722822_2129300","value":"2129300"},{"content":"\n                <label for=\"resp722822_2129302\">\n                    <span class=\"under_an\">D</span>. \\[(1;3)\\].                </label>\n            ","id":"resp722822_2129302","value":"2129302"}]},{"content":"\n    Trong không gian với hệ tọa độ \\[Oxyz\\], cho \\[M(0;4;0)\\] và hai đường thẳng \\[{{\\Delta }_{1}}: \\frac{x-2}{1}=\\frac{y-1}{-1}=\\frac{z}{1}\\]; \\[{{\\Delta }_{2}}: \\frac{x}{2}=\\frac{y+1}{1}=\\frac{z}{-2}\\]. Đường thẳng \\[d\\] đi qua \\[M\\] cắt \\[{{\\Delta }_{1}},{{\\Delta }_{2}}\\] lần lượt tại \\[A,B\\]. Độ dài đoạn \\[AB\\] bằng bao nhiêu?","info":"\n\t4.\n      ","answers":[{"content":"\n                <label for=\"resp722834_2129348\">\n                    <span class=\"under_an\">A</span>. \\[AB=2\\].                </label>\n            ","id":"resp722834_2129348","value":"2129348"},{"content":"\n                <label for=\"resp722834_2129352\">\n                    <span class=\"under_an\">B</span>. \\[AB=\\sqrt{13}\\].                </label>\n            ","id":"resp722834_2129352","value":"2129352"},{"content":"\n                <label for=\"resp722834_2129350\">\n                    <span class=\"under_an\">C</span>. \\[AB=3\\].                </label>\n            ","id":"resp722834_2129350","value":"2129350"},{"content":"\n                <label for=\"resp722834_2129354\">\n                    <span class=\"under_an\">D</span>. \\[AB=\\sqrt{6}\\].                </label>\n            ","id":"resp722834_2129354","value":"2129354"}]},{"content":"\n    Cho \\[f(x)\\] là hàm số lẻ, xác định và liên tục trên \\[\\mathbb{R}\\]. Biết \\[\\int\\limits_{3}^{5}{f(x)dx=1}\\] và \\[\\int\\limits_{-2}^{1}{f(-3x)dx=3}\\]. Khi đó tích phân \\[I=\\int\\limits_{-6}^{5}{f(x)dx}\\] bằng bao nhiêu?","info":"\n\t5.\n      ","answers":[{"content":"\n                <label for=\"resp722826_2129318\">\n                    <span class=\"under_an\">A</span>. \\[I=0\\].                </label>\n            ","id":"resp722826_2129318","value":"2129318"},{"content":"\n                <label for=\"resp722826_2129316\">\n                    <span class=\"under_an\">B</span>. \\[I=-8\\].                </label>\n            ","id":"resp722826_2129316","value":"2129316"},{"content":"\n                <label for=\"resp722826_2129322\">\n                    <span class=\"under_an\">C</span>. \\[I=10\\].                </label>\n            ","id":"resp722826_2129322","value":"2129322"},{"content":"\n                <label for=\"resp722826_2129320\">\n                    <span class=\"under_an\">D</span>. \\[I=2\\].                </label>\n            ","id":"resp722826_2129320","value":"2129320"}]},{"content":"\n    Có bao nhiêu giá trị nguyên của \\[m\\] để phương trình \\[5{{\\sin }^{2}}x={{m}^{2}}-4m\\] có nghiệm?","info":"\n\t6.\n      ","answers":[{"content":"\n                <label for=\"resp722840_2129378\">\n                    <span class=\"under_an\">A</span>. vô số.                </label>\n            ","id":"resp722840_2129378","value":"2129378"},{"content":"\n                <label for=\"resp722840_2129376\">\n                    <span class=\"under_an\">B</span>. \\[5\\].                </label>\n            ","id":"resp722840_2129376","value":"2129376"},{"content":"\n                <label for=\"resp722840_2129374\">\n                    <span class=\"under_an\">C</span>. \\[4\\].                </label>\n            ","id":"resp722840_2129374","value":"2129374"},{"content":"\n                <label for=\"resp722840_2129372\">\n                    <span class=\"under_an\">D</span>. \\[3\\].                </label>\n            ","id":"resp722840_2129372","value":"2129372"}]},{"content":"\n    Trong không gian với hệ tọa độ \\[Oxyz\\], cho hai đường thẳng \\[{{\\Delta }_{1}}: \\left\\{ \\begin{array}{l}\n x=t \\\\\n y=-1+2t \\\\\n z=2-3t \n \\end{array} \\right. \\] và \\[{{\\Delta }_{2}}: \\frac{x+3}{4}=\\frac{y}{1}=\\frac{z+3}{2}\\]. Khẳng định nào sau đây đúng?","info":"\n\t7.\n      ","answers":[{"content":"\n                <label for=\"resp722820_2129296\">\n                    <span class=\"under_an\">A</span>. \\[{{\\Delta }_{1}}\\] và \\[{{\\Delta }_{2}}\\] chéo nhau và vuông góc với nhau.                </label>\n            ","id":"resp722820_2129296","value":"2129296"},{"content":"\n                <label for=\"resp722820_2129292\">\n                    <span class=\"under_an\">B</span>. \\[{{\\Delta }_{1}}\\] cắt và không vuông góc với \\[{{\\Delta }_{2}}\\].                </label>\n            ","id":"resp722820_2129292","value":"2129292"},{"content":"\n                <label for=\"resp722820_2129298\">\n                    <span class=\"under_an\">C</span>. \\[{{\\Delta }_{1}}\\] cắt và vuông góc với \\[{{\\Delta }_{2}}\\].                </label>\n            ","id":"resp722820_2129298","value":"2129298"},{"content":"\n                <label for=\"resp722820_2129294\">\n                    <span class=\"under_an\">D</span>. \\[{{\\Delta }_{1}}\\] song song với \\[{{\\Delta }_{2}}\\].                </label>\n            ","id":"resp722820_2129294","value":"2129294"}]},{"content":"\n    Cho nửa đường tròn đường kính \\[AB\\] và điểm \\[C\\] thay đổi trên nửa đường tròn đó sao cho \\[\\widehat{CAB}=\\alpha \\]. Gọi \\[H\\] là hình chiếu vuông góc của \\[C\\] lên \\[AB\\]. Biết \\[\\alpha ={{\\alpha }_{0}}\\] thì thể tích khối tròn xoay tạo thành khi quay tam giác \\[ACH\\] quanh trục \\[AB\\] đạt giá trị lớn nhất. Khi đó \\[{{\\alpha }_{0}}\\] bằng","info":"\n\t8.\n      ","answers":[{"content":"\n                <label for=\"resp722852_2129426\">\n                    <span class=\"under_an\">A</span>. \\[{{\\alpha }_{0}}=\\arctan \\sqrt{2}\\]                </label>\n            ","id":"resp722852_2129426","value":"2129426"},{"content":"\n                <label for=\"resp722852_2129420\">\n                    <span class=\"under_an\">B</span>. \\[{{\\alpha }_{0}}={{30}^{0}}\\]                </label>\n            ","id":"resp722852_2129420","value":"2129420"},{"content":"\n                <label for=\"resp722852_2129422\">\n                    <span class=\"under_an\">C</span>. \\[{{\\alpha }_{0}}=\\arctan \\frac{1}{\\sqrt{2}}\\]                </label>\n            ","id":"resp722852_2129422","value":"2129422"},{"content":"\n                <label for=\"resp722852_2129424\">\n                    <span class=\"under_an\">D</span>. \\[{{\\alpha }_{0}}={{60}^{0}}\\]                </label>\n            ","id":"resp722852_2129424","value":"2129424"}]},{"content":"\n    Gọi \\[S\\] là tập các số có bốn chữ số khác nhau được lập nên từ các chữ số \\[0;1;2;3;5;6;9\\]. Chọn một số từ tập \\[S\\], tính xác suất để số được chọn luôn có mặt chữ số \\[9\\] và có tổng các chữ số là một số chẵn.","info":"\n\t9.\n      ","answers":[{"content":"\n                <label for=\"resp722850_2129416\">\n                    <span class=\"under_an\">A</span>. \\[\\frac{4}{21}\\].                </label>\n            ","id":"resp722850_2129416","value":"2129416"},{"content":"\n                <label for=\"resp722850_2129418\">\n                    <span class=\"under_an\">B</span>. \\[\\frac{1}{3}\\].                </label>\n            ","id":"resp722850_2129418","value":"2129418"},{"content":"\n                <label for=\"resp722850_2129412\">\n                    <span class=\"under_an\">C</span>. \\[\\frac{17}{60}\\].                </label>\n            ","id":"resp722850_2129412","value":"2129412"},{"content":"\n                <label for=\"resp722850_2129414\">\n                    <span class=\"under_an\">D</span>. \\[\\frac{17}{105}\\].                </label>\n            ","id":"resp722850_2129414","value":"2129414"}]},{"content":"\n    Cho khối chóp \\[S. ABCD\\] có thể tích bằng \\[V\\]. Gọi \\[M,N,P,Q\\] lần lượt là trung điểm của \\[SA,SB,SC,SD\\]. Thể tích của khối chóp \\[S. MNPQ\\] bằng","info":"\n\t10.\n      ","answers":[{"content":"\n                <label for=\"resp722830_2129332\">\n                    <span class=\"under_an\">A</span>. \\[\\frac{V}{16}\\].                </label>\n            ","id":"resp722830_2129332","value":"2129332"},{"content":"\n                <label for=\"resp722830_2129338\">\n                    <span class=\"under_an\">B</span>. \\[\\frac{V}{2}\\].                </label>\n            ","id":"resp722830_2129338","value":"2129338"},{"content":"\n                <label for=\"resp722830_2129336\">\n                    <span class=\"under_an\">C</span>. \\[\\frac{V}{4}\\].                </label>\n            ","id":"resp722830_2129336","value":"2129336"},{"content":"\n                <label for=\"resp722830_2129334\">\n                    <span class=\"under_an\">D</span>. \\[\\frac{V}{8}\\].                </label>\n            ","id":"resp722830_2129334","value":"2129334"}]},{"content":"\n    Tìm tất cả các giá trị của tham số thực \\[m\\] để hàm số \\[y=\\frac{{{x}^{3}}}{3}-m{{x}^{2}}+({{m}^{2}}-1)x-3\\] đạt cực đại tại \\[x=2\\].","info":"\n\t11.\n      ","answers":[{"content":"\n                <label for=\"resp722816_2129278\">\n                    <span class=\"under_an\">A</span>. \\[m=1\\].                </label>\n            ","id":"resp722816_2129278","value":"2129278"},{"content":"\n                <label for=\"resp722816_2129280\">\n                    <span class=\"under_an\">B</span>. \\[m\\in \\left\\{ 1;3 \\right\\}\\].                </label>\n            ","id":"resp722816_2129280","value":"2129280"},{"content":"\n                <label for=\"resp722816_2129282\">\n                    <span class=\"under_an\">C</span>. \\[m=0\\].                </label>\n            ","id":"resp722816_2129282","value":"2129282"},{"content":"\n                <label for=\"resp722816_2129276\">\n                    <span class=\"under_an\">D</span>. \\[m=3\\].                </label>\n            ","id":"resp722816_2129276","value":"2129276"}]},{"content":"\n    Gọi \\[A,B,C\\] là ba điểm cực trị của đồ thị hàm số \\[y={{x}^{4}}-2{{x}^{2}}+2\\]. Khi đó diện tích \\[S\\] của tam giác \\[ABC\\] bằng bao nhiêu?","info":"\n\t12.\n      ","answers":[{"content":"\n                <label for=\"resp722818_2129288\">\n                    <span class=\"under_an\">A</span>. \\[S=4\\].                </label>\n            ","id":"resp722818_2129288","value":"2129288"},{"content":"\n                <label for=\"resp722818_2129284\">\n                    <span class=\"under_an\">B</span>. \\[S=2\\].                </label>\n            ","id":"resp722818_2129284","value":"2129284"},{"content":"\n                <label for=\"resp722818_2129286\">\n                    <span class=\"under_an\">C</span>. \\[S=1\\].                </label>\n            ","id":"resp722818_2129286","value":"2129286"},{"content":"\n                <label for=\"resp722818_2129290\">\n                    <span class=\"under_an\">D</span>. \\[S=3\\].                </label>\n            ","id":"resp722818_2129290","value":"2129290"}]},{"content":"\n    Cần chọn ra 3 học sinh từ một lớp 20 học sinh để làm các chức vụ lớp trưởng, bí thư, lớp phó học tập. Hỏi có bao nhiêu cách chọn?","info":"\n\t13.\n      ","answers":[{"content":"\n                <label for=\"resp722836_2129358\">\n                    <span class=\"under_an\">A</span>. \\[C_{20}^{3}\\].                </label>\n            ","id":"resp722836_2129358","value":"2129358"},{"content":"\n                <label for=\"resp722836_2129356\">\n                    <span class=\"under_an\">B</span>. \\[60\\].                </label>\n            ","id":"resp722836_2129356","value":"2129356"},{"content":"\n                <label for=\"resp722836_2129362\">\n                    <span class=\"under_an\">C</span>. \\[{{20}^{3}}\\].                </label>\n            ","id":"resp722836_2129362","value":"2129362"},{"content":"\n                <label for=\"resp722836_2129360\">\n                    <span class=\"under_an\">D</span>. \\[A_{20}^{3}\\].                </label>\n            ","id":"resp722836_2129360","value":"2129360"}]},{"content":"\n    Nếu \\[f(1)=12\\], \\[f'(x)\\] liên tục trên \\[\\left[ 1;4 \\right]\\] và \\[\\int\\limits_{1}^{4}{f'(x)dx=17}\\]. Khi đó, giá trị của \\[f(4)\\] bằng","info":"\n\t14.\n      ","answers":[{"content":"\n                <label for=\"resp722844_2129388\">\n                    <span class=\"under_an\">A</span>. \\[5\\].                </label>\n            ","id":"resp722844_2129388","value":"2129388"},{"content":"\n                <label for=\"resp722844_2129394\">\n                    <span class=\"under_an\">B</span>. \\[29\\].                </label>\n            ","id":"resp722844_2129394","value":"2129394"},{"content":"\n                <label for=\"resp722844_2129390\">\n                    <span class=\"under_an\">C</span>. \\[9\\].                </label>\n            ","id":"resp722844_2129390","value":"2129390"},{"content":"\n                <label for=\"resp722844_2129392\">\n                    <span class=\"under_an\">D</span>. \\[19\\].                </label>\n            ","id":"resp722844_2129392","value":"2129392"}]},{"content":"\n    Cho \\[f(x)=x+\\frac{{{x}^{2}}}{2}+\\frac{{{x}^{3}}}{3}+... +\\frac{{{x}^{n+1}}}{n+1}\\] với \\[n\\in \\mathbb{N}\\].\n Tìm giá trị nhỏ nhất của \\[n\\] để \\[\\sqrt{\\underset{x\\to 2}{\\mathop{\\lim }}\\,f'(x)}>2018\\].","info":"\n\t15.\n      ","answers":[{"content":"\n                <label for=\"resp722838_2129368\">\n                    <span class=\"under_an\">A</span>. \\[20\\].                </label>\n            ","id":"resp722838_2129368","value":"2129368"},{"content":"\n                <label for=\"resp722838_2129370\">\n                    <span class=\"under_an\">B</span>. \\[21\\].                </label>\n            ","id":"resp722838_2129370","value":"2129370"},{"content":"\n                <label for=\"resp722838_2129366\">\n                    <span class=\"under_an\">C</span>. \\[22\\].                </label>\n            ","id":"resp722838_2129366","value":"2129366"},{"content":"\n                <label for=\"resp722838_2129364\">\n                    <span class=\"under_an\">D</span>. \\[10\\].                </label>\n            ","id":"resp722838_2129364","value":"2129364"}]},{"content":"\n    Cho tam giác \\[ABC\\] vuông tại \\[A\\] nằm trong mặt phẳng \\[(P)\\] có \\[\\widehat{ABC}={{30}^{0}}\\], chiều cao \\[AH=a\\] (\\[AH\\bot BC,H\\in BC\\]). Quay \\[(P)\\] quanh cạnh \\[AB\\], đường gấp khúc \\[BCA\\] tạo thành hình nón tròn xoay. Thể tích của khối nón tạo thành là","info":"\n\t16.\n      ","answers":[{"content":"\n                <label for=\"resp722854_2129434\">\n                    <span class=\"under_an\">A</span>. \\[\\frac{4{{a}^{3}}\\pi }{9}\\].                </label>\n            ","id":"resp722854_2129434","value":"2129434"},{"content":"\n                <label for=\"resp722854_2129428\">\n                    <span class=\"under_an\">B</span>. \\[\\frac{8{{a}^{3}}\\pi }{3}\\].                </label>\n            ","id":"resp722854_2129428","value":"2129428"},{"content":"\n                <label for=\"resp722854_2129432\">\n                    <span class=\"under_an\">C</span>. \\[\\frac{8{{a}^{3}}\\pi }{9}\\].                </label>\n            ","id":"resp722854_2129432","value":"2129432"},{"content":"\n                <label for=\"resp722854_2129430\">\n                    <span class=\"under_an\">D</span>. \\[\\frac{4{{a}^{3}}\\pi }{3}\\].                </label>\n            ","id":"resp722854_2129430","value":"2129430"}]},{"content":"\n    Cho hàm số \\[f(x)=\\frac{4m}{\\pi }+{{\\sin }^{2}}x\\]. Tìm \\[m\\] để nguyên hàm \\[F(x)\\] của \\[f(x)\\] thỏa mãn \\[F(0)=1\\] và \\[F\\left( \\frac{\\pi }{4} \\right)=\\frac{\\pi }{8}\\].","info":"\n\t17.\n      ","answers":[{"content":"\n                <label for=\"resp722824_2129308\">\n                    <span class=\"under_an\">A</span>. \\[m=\\frac{3}{4}\\].                </label>\n            ","id":"resp722824_2129308","value":"2129308"},{"content":"\n                <label for=\"resp722824_2129310\">\n                    <span class=\"under_an\">B</span>. \\[m=\\frac{4}{3}\\].                </label>\n            ","id":"resp722824_2129310","value":"2129310"},{"content":"\n                <label for=\"resp722824_2129314\">\n                    <span class=\"under_an\">C</span>. \\[m=-\\frac{4}{3}\\].                </label>\n            ","id":"resp722824_2129314","value":"2129314"},{"content":"\n                <label for=\"resp722824_2129312\">\n                    <span class=\"under_an\">D</span>. \\[m=-\\frac{3}{4}\\].                </label>\n            ","id":"resp722824_2129312","value":"2129312"}]},{"content":"\n    Cho hình nón \\[(N)\\] có đỉnh là \\[S\\], đường tròn đáy là \\[(O,R)\\]. Góc ở đỉnh của hình nón là \\[{{120}^{0}}\\]. Hình chóp đều \\[S. ABC\\] có \\[A,B,C\\] thuộc đường tròn \\[(O,R)\\] có thể tích là","info":"\n\t18.\n      ","answers":[{"content":"\n                <label for=\"resp722832_2129346\">\n                    <span class=\"under_an\">A</span>. \\[\\frac{{{R}^{3}}\\sqrt{3}}{6}\\].                </label>\n            ","id":"resp722832_2129346","value":"2129346"},{"content":"\n                <label for=\"resp722832_2129340\">\n                    <span class=\"under_an\">B</span>. \\[\\frac{{{R}^{3}}}{4}\\].                </label>\n            ","id":"resp722832_2129340","value":"2129340"},{"content":"\n                <label for=\"resp722832_2129344\">\n                    <span class=\"under_an\">C</span>. \\[\\frac{{{R}^{3}}\\sqrt{3}}{4}\\].                </label>\n            ","id":"resp722832_2129344","value":"2129344"},{"content":"\n                <label for=\"resp722832_2129342\">\n                    <span class=\"under_an\">D</span>. \\[\\frac{3{{R}^{3}}}{4}\\].                </label>\n            ","id":"resp722832_2129342","value":"2129342"}]},{"content":"\n    Cho hai số phức \\[{{z}_{1}},{{z}_{2}}\\] thỏa mãn \\[\\left| {{z}_{1}} \\right|=2\\left| {{z}_{2}} \\right|=\\sqrt{2}\\]. Khi đó \\[T={{\\left| {{z}_{1}}+{{z}_{2}} \\right|}^{2}}+{{\\left| {{z}_{1}}-{{z}_{2}} \\right|}^{2}}\\] bằng bao nhiêu?","info":"\n\t19.\n      ","answers":[{"content":"\n                <label for=\"resp722828_2129326\">\n                    <span class=\"under_an\">A</span>. \\[3\\].                </label>\n            ","id":"resp722828_2129326","value":"2129326"},{"content":"\n                <label for=\"resp722828_2129328\">\n                    <span class=\"under_an\">B</span>. \\[5\\].                </label>\n            ","id":"resp722828_2129328","value":"2129328"},{"content":"\n                <label for=\"resp722828_2129324\">\n                    <span class=\"under_an\">C</span>. \\[3\\sqrt{2}\\].                </label>\n            ","id":"resp722828_2129324","value":"2129324"},{"content":"\n                <label for=\"resp722828_2129330\">\n                    <span class=\"under_an\">D</span>. \\[5\\sqrt{2}\\].                </label>\n            ","id":"resp722828_2129330","value":"2129330"}]},{"content":"\n    Cho hình chóp đều \\[S. ABCD\\] có cạnh đáy bằng \\[a\\], khoảng cách giữa hai đường thẳng \\[SB\\] và \\[CD\\] bằng \\[\\frac{a}{\\sqrt{2}}\\]. Thể tích \\[V\\] của khối chóp \\[S. ABCD\\] là","info":"\n\t20.\n      ","answers":[{"content":"\n                <label for=\"resp722842_2129380\">\n                    <span class=\"under_an\">A</span>. \\[V=\\frac{{{a}^{3}}}{2}\\].                </label>\n            ","id":"resp722842_2129380","value":"2129380"},{"content":"\n                <label for=\"resp722842_2129382\">\n                    <span class=\"under_an\">B</span>. \\[V=\\frac{{{a}^{3}}\\sqrt{2}}{3}\\].                </label>\n            ","id":"resp722842_2129382","value":"2129382"},{"content":"\n                <label for=\"resp722842_2129384\">\n                    <span class=\"under_an\">C</span>. \\[V=\\frac{{{a}^{3}}}{6}\\].                </label>\n            ","id":"resp722842_2129384","value":"2129384"},{"content":"\n                <label for=\"resp722842_2129386\">\n                    <span class=\"under_an\">D</span>. \\[V=\\frac{{{a}^{3}}\\sqrt{2}}{9}\\].                </label>\n            ","id":"resp722842_2129386","value":"2129386"}]}]}]